<?xml version="1.0" encoding="UTF-8"?>
<Form xmlns="http://v8.1c.ru/8.3/xcf/logform" xmlns:app="http://v8.1c.ru/8.2/managed-application/core" xmlns:cfg="http://v8.1c.ru/8.1/data/enterprise/current-config" xmlns:dcscor="http://v8.1c.ru/8.1/data-composition-system/core" xmlns:dcsset="http://v8.1c.ru/8.1/data-composition-system/settings" xmlns:ent="http://v8.1c.ru/8.1/data/enterprise" xmlns:lf="http://v8.1c.ru/8.2/managed-application/logform" xmlns:style="http://v8.1c.ru/8.1/data/ui/style" xmlns:sys="http://v8.1c.ru/8.1/data/ui/fonts/system" xmlns:v8="http://v8.1c.ru/8.1/data/core" xmlns:v8ui="http://v8.1c.ru/8.1/data/ui" xmlns:web="http://v8.1c.ru/8.1/data/ui/colors/web" xmlns:win="http://v8.1c.ru/8.1/data/ui/colors/windows" xmlns:xr="http://v8.1c.ru/8.3/xcf/readable" xmlns:xs="http://www.w3.org/2001/XMLSchema" xmlns:xsi="http://www.w3.org/2001/XMLSchema-instance" version="2.4">
	<Title>
		<v8:item>
			<v8:lang>ru</v8:lang>
			<v8:content>Контрагенты</v8:content>
		</v8:item>
	</Title>
	<AutoSaveDataInSettings>Use</AutoSaveDataInSettings>
	<CommandBarLocation>None</CommandBarLocation>
	<ScalingMode>Compact</ScalingMode>
	<AutoCommandBar name="ФормаКоманднаяПанель" id="-1"/>
	<Events>
		<Event name="OnCreateAtServer">ПриСозданииНаСервере</Event>
	</Events>
	<ChildItems>
		<UsualGroup name="Группа1" id="26">
			<Group>Horizontal</Group>
			<Representation>None</Representation>
			<ShowTitle>false</ShowTitle>
			<ExtendedTooltip name="Группа1РасширеннаяПодсказка" id="27"/>
			<ChildItems>
				<UsualGroup name="Группа2" id="28">
					<Group>Vertical</Group>
					<Representation>None</Representation>
					<ShowTitle>false</ShowTitle>
					<ExtendedTooltip name="Группа2РасширеннаяПодсказка" id="29"/>
					<ChildItems>
						<UsualGroup name="Группа7" id="209">
							<Group>Horizontal</Group>
							<Representation>None</Representation>
							<ShowTitle>false</ShowTitle>
							<ExtendedTooltip name="Группа7РасширеннаяПодсказка" id="210"/>
							<ChildItems>
								<UsualGroup name="Группа8" id="211">
									<Group>Vertical</Group>
									<Representation>None</Representation>
									<ShowTitle>false</ShowTitle>
									<ExtendedTooltip name="Группа8РасширеннаяПодсказка" id="212"/>
									<ChildItems>
										<UsualGroup name="Группа4" id="129">
											<Group>Horizontal</Group>
											<Representation>None</Representation>
											<ShowTitle>false</ShowTitle>
											<ExtendedTooltip name="Группа4РасширеннаяПодсказка" id="130"/>
											<ChildItems>
												<CheckBoxField name="ОтборИмяИспользование" id="171">
													<DataPath>ОтборИмяИспользование</DataPath>
													<TitleLocation>None</TitleLocation>
													<CheckBoxType>Auto</CheckBoxType>
													<ContextMenu name="ОтборИмяИспользованиеКонтекстноеМеню" id="172"/>
													<ExtendedTooltip name="ОтборИмяИспользованиеРасширеннаяПодсказка" id="173"/>
												</CheckBoxField>
												<InputField name="ОтборИмя" id="165">
													<DataPath>ОтборИмя</DataPath>
													<ContextMenu name="ОтборИмяКонтекстноеМеню" id="166"/>
													<ExtendedTooltip name="ОтборИмяРасширеннаяПодсказка" id="167"/>
												</InputField>
												<CheckBoxField name="ОтборПолноеИмяИспользование" id="177">
													<DataPath>ОтборПолноеИмяИспользование</DataPath>
													<TitleLocation>None</TitleLocation>
													<CheckBoxType>Auto</CheckBoxType>
													<ContextMenu name="ОтборПолноеИмяИспользованиеКонтекстноеМеню" id="178"/>
													<ExtendedTooltip name="ОтборПолноеИмяИспользованиеРасширеннаяПодсказка" id="179"/>
												</CheckBoxField>
												<InputField name="ОтборПолноеИмя" id="206">
													<DataPath>ОтборПолноеИмя</DataPath>
													<ContextMenu name="ОтборПолноеИмяКонтекстноеМеню" id="207"/>
													<ExtendedTooltip name="ОтборПолноеИмяРасширеннаяПодсказка" id="208"/>
												</InputField>
												<CheckBoxField name="ОтборФИОИспользование" id="180">
													<DataPath>ОтборФИОИспользование</DataPath>
													<TitleLocation>None</TitleLocation>
													<CheckBoxType>Auto</CheckBoxType>
													<ContextMenu name="ОтборФИОИспользованиеКонтекстноеМеню" id="181"/>
													<ExtendedTooltip name="ОтборФИОИспользованиеРасширеннаяПодсказка" id="182"/>
												</CheckBoxField>
												<InputField name="ОтборФИО" id="162">
													<DataPath>ОтборФИО</DataPath>
													<ContextMenu name="ОтборФИОКонтекстноеМеню" id="163"/>
													<ExtendedTooltip name="ОтборФИОРасширеннаяПодсказка" id="164"/>
												</InputField>
											</ChildItems>
										</UsualGroup>
										<UsualGroup name="Группа6" id="189">
											<Group>Horizontal</Group>
											<Representation>None</Representation>
											<ShowTitle>false</ShowTitle>
											<ExtendedTooltip name="Группа6РасширеннаяПодсказка" id="190"/>
											<ChildItems>
												<CheckBoxField name="ОтборИННИспользование" id="174">
													<DataPath>ОтборИННИспользование</DataPath>
													<TitleLocation>None</TitleLocation>
													<CheckBoxType>Auto</CheckBoxType>
													<ContextMenu name="ОтборИННИспользованиеКонтекстноеМеню" id="175"/>
													<ExtendedTooltip name="ОтборИННИспользованиеРасширеннаяПодсказка" id="176"/>
												</CheckBoxField>
												<InputField name="ОтборИНН" id="203">
													<DataPath>ОтборИНН</DataPath>
													<ContextMenu name="ОтборИННКонтекстноеМеню" id="204"/>
													<ExtendedTooltip name="ОтборИННРасширеннаяПодсказка" id="205"/>
												</InputField>
												<CheckBoxField name="ОтборРегионИспользование" id="200">
													<DataPath>ОтборРегионИспользование</DataPath>
													<TitleLocation>None</TitleLocation>
													<CheckBoxType>Auto</CheckBoxType>
													<ContextMenu name="ОтборРегионИспользованиеКонтекстноеМеню" id="201"/>
													<ExtendedTooltip name="ОтборРегионИспользованиеРасширеннаяПодсказка" id="202"/>
												</CheckBoxField>
												<InputField name="ОтборРегион" id="197">
													<DataPath>ОтборРегион</DataPath>
													<ContextMenu name="ОтборРегионКонтекстноеМеню" id="198"/>
													<ExtendedTooltip name="ОтборРегионРасширеннаяПодсказка" id="199"/>
												</InputField>
												<CheckBoxField name="ОтборРайонИспользование" id="194">
													<DataPath>ОтборРайонИспользование</DataPath>
													<TitleLocation>None</TitleLocation>
													<CheckBoxType>Auto</CheckBoxType>
													<ContextMenu name="ОтборРайонИспользованиеКонтекстноеМеню" id="195"/>
													<ExtendedTooltip name="ОтборРайонИспользованиеРасширеннаяПодсказка" id="196"/>
												</CheckBoxField>
												<InputField name="ОтборРайон" id="191">
													<DataPath>ОтборРайон</DataPath>
													<ChoiceParameterLinks>
														<xr:Link>
															<xr:Name>Отбор.Регион</xr:Name>
															<xr:DataPath xsi:type="xs:string">ОтборРегион</xr:DataPath>
															<xr:ValueChange>Clear</xr:ValueChange>
														</xr:Link>
													</ChoiceParameterLinks>
													<ContextMenu name="ОтборРайонКонтекстноеМеню" id="192"/>
													<ExtendedTooltip name="ОтборРайонРасширеннаяПодсказка" id="193"/>
												</InputField>
											</ChildItems>
										</UsualGroup>
									</ChildItems>
								</UsualGroup>
								<UsualGroup name="Группа9" id="213">
									<Group>Vertical</Group>
									<Representation>None</Representation>
									<ShowTitle>false</ShowTitle>
									<ExtendedTooltip name="Группа9РасширеннаяПодсказка" id="214"/>
									<ChildItems>
										<Button name="СписокВетисКомандаНайти" id="183">
											<Type>UsualButton</Type>
											<Representation>PictureAndText</Representation>
											<CommandName>Form.Command.КомандаНайти</CommandName>
											<ExtendedTooltip name="СписокВетисКомандаНайтиРасширеннаяПодсказка" id="184"/>
										</Button>
										<InputField name="МаксимальноеКоличество" id="147">
											<DataPath>МаксимальноеКоличество</DataPath>
											<Width>2</Width>
											<ContextMenu name="МаксимальноеКоличествоКонтекстноеМеню" id="148"/>
											<ExtendedTooltip name="МаксимальноеКоличествоРасширеннаяПодсказка" id="149"/>
										</InputField>
									</ChildItems>
								</UsualGroup>
							</ChildItems>
						</UsualGroup>
						<UsualGroup name="Группа5" id="185">
							<Representation>None</Representation>
							<ShowTitle>false</ShowTitle>
							<ExtendedTooltip name="Группа5РасширеннаяПодсказка" id="186"/>
							<ChildItems>
								<InputField name="guid" id="142">
									<DataPath>ОтборGuid</DataPath>
									<ContextMenu name="guidКонтекстноеМеню" id="143"/>
									<ExtendedTooltip name="guidРасширеннаяПодсказка" id="144"/>
									<Events>
										<Event name="OnChange">guidПриИзменении</Event>
									</Events>
								</InputField>
								<Button name="КомандаНайтиПоGuid" id="187">
									<Type>UsualButton</Type>
									<Representation>PictureAndText</Representation>
									<CommandName>Form.Command.КомандаНайтиПоGuid</CommandName>
									<ExtendedTooltip name="КомандаНайтиПоGuidРасширеннаяПодсказка" id="188"/>
								</Button>
							</ChildItems>
						</UsualGroup>
						<Table name="СписокВетис" id="1">
							<Representation>List</Representation>
							<ReadOnly>true</ReadOnly>
							<ChangeRowSet>false</ChangeRowSet>
							<ChangeRowOrder>false</ChangeRowOrder>
							<HeightInTableRows>1</HeightInTableRows>
							<AutoInsertNewRow>true</AutoInsertNewRow>
							<EnableStartDrag>true</EnableStartDrag>
							<EnableDrag>true</EnableDrag>
							<DataPath>СписокВетис</DataPath>
							<CommandSet>
								<ExcludedCommand>Change</ExcludedCommand>
							</CommandSet>
							<RowFilter xsi:nil="true"/>
							<ContextMenu name="СписокВетисКонтекстноеМеню" id="2"/>
							<AutoCommandBar name="СписокВетисКоманднаяПанель" id="3"/>
							<ExtendedTooltip name="СписокВетисРасширеннаяПодсказка" id="4"/>
							<SearchStringAddition name="СписокВетисСтрокаПоиска" id="5">
								<AdditionSource>
									<Item>СписокВетис</Item>
									<Type>SearchStringRepresentation</Type>
								</AdditionSource>
								<ContextMenu name="СписокВетисСтрокаПоискаКонтекстноеМеню" id="6"/>
								<ExtendedTooltip name="СписокВетисСтрокаПоискаРасширеннаяПодсказка" id="7"/>
							</SearchStringAddition>
							<ViewStatusAddition name="СписокВетисСостояниеПросмотра" id="8">
								<AdditionSource>
									<Item>СписокВетис</Item>
									<Type>ViewStatusRepresentation</Type>
								</AdditionSource>
								<ContextMenu name="СписокВетисСостояниеПросмотраКонтекстноеМеню" id="9"/>
								<ExtendedTooltip name="СписокВетисСостояниеПросмотраРасширеннаяПодсказка" id="10"/>
							</ViewStatusAddition>
							<SearchControlAddition name="СписокВетисУправлениеПоиском" id="11">
								<AdditionSource>
									<Item>СписокВетис</Item>
									<Type>SearchControl</Type>
								</AdditionSource>
								<ContextMenu name="СписокВетисУправлениеПоискомКонтекстноеМеню" id="12"/>
								<ExtendedTooltip name="СписокВетисУправлениеПоискомРасширеннаяПодсказка" id="13"/>
							</SearchControlAddition>
							<Events>
								<Event name="Selection">СписокВетисВыбор</Event>
							</Events>
							<ChildItems>
								<InputField name="СписокВетисname" id="117">
									<DataPath>СписокВетис.name</DataPath>
									<EditMode>EnterOnInput</EditMode>
									<ContextMenu name="СписокВетисnameКонтекстноеМеню" id="118"/>
									<ExtendedTooltip name="СписокВетисnameРасширеннаяПодсказка" id="119"/>
								</InputField>
								<InputField name="СписокВетисinn" id="114">
									<DataPath>СписокВетис.inn</DataPath>
									<EditMode>EnterOnInput</EditMode>
									<ContextMenu name="СписокВетисinnКонтекстноеМеню" id="115"/>
									<ExtendedTooltip name="СписокВетисinnРасширеннаяПодсказка" id="116"/>
								</InputField>
								<InputField name="СписокВетисtype" id="99">
									<DataPath>СписокВетис.type</DataPath>
									<EditMode>EnterOnInput</EditMode>
									<ContextMenu name="СписокВетисtypeКонтекстноеМеню" id="100"/>
									<ExtendedTooltip name="СписокВетисtypeРасширеннаяПодсказка" id="101"/>
								</InputField>
								<InputField name="СписокВетисaddress" id="102">
									<DataPath>СписокВетис.address</DataPath>
									<EditMode>EnterOnInput</EditMode>
									<ContextMenu name="СписокВетисaddressКонтекстноеМеню" id="103"/>
									<ExtendedTooltip name="СписокВетисaddressРасширеннаяПодсказка" id="104"/>
								</InputField>
							</ChildItems>
						</Table>
					</ChildItems>
				</UsualGroup>
				<UsualGroup name="Группа3" id="30">
					<Group>Vertical</Group>
					<Representation>None</Representation>
					<ShowTitle>false</ShowTitle>
					<ExtendedTooltip name="Группа3РасширеннаяПодсказка" id="31"/>
					<ChildItems>
						<InputField name="ПолеОтбор" id="126">
							<DataPath>СправочникСписок.Filter[0].RightValue</DataPath>
							<Visible>false</Visible>
							<Title>
								<v8:item>
									<v8:lang>ru</v8:lang>
									<v8:content>Отбор</v8:content>
								</v8:item>
							</Title>
							<ContextMenu name="ПолеОтборКонтекстноеМеню" id="127"/>
							<ExtendedTooltip name="ПолеОтборРасширеннаяПодсказка" id="128"/>
						</InputField>
						<Table name="СправочникСписок" id="34">
							<Representation>List</Representation>
							<ChangeRowSet>false</ChangeRowSet>
							<ChangeRowOrder>false</ChangeRowOrder>
							<HeightInTableRows>1</HeightInTableRows>
							<EnableStartDrag>true</EnableStartDrag>
							<DataPath>СправочникСписок</DataPath>
							<RowPictureDataPath>СправочникСписок.DefaultPicture</RowPictureDataPath>
							<SearchStringLocation>Top</SearchStringLocation>
							<AutoRefresh>false</AutoRefresh>
							<AutoRefreshPeriod>60</AutoRefreshPeriod>
							<Period>
								<v8:variant xsi:type="v8:StandardPeriodVariant">Custom</v8:variant>
								<v8:startDate>0001-01-01T00:00:00</v8:startDate>
								<v8:endDate>0001-01-01T00:00:00</v8:endDate>
							</Period>
							<ChoiceFoldersAndItems>Items</ChoiceFoldersAndItems>
							<RestoreCurrentRow>false</RestoreCurrentRow>
							<TopLevelParent xsi:nil="true"/>
							<ShowRoot>true</ShowRoot>
							<AllowRootChoice>false</AllowRootChoice>
							<UpdateOnDataChange>Auto</UpdateOnDataChange>
							<ContextMenu name="СправочникСписокКонтекстноеМеню" id="35"/>
							<AutoCommandBar name="СправочникСписокКоманднаяПанель" id="36">
								<ChildItems>
									<Button name="СправочникСписокКомандаДобавить" id="145">
										<Type>CommandBarButton</Type>
										<CommandName>Form.Command.КомандаСправочникДобавить</CommandName>
										<ExtendedTooltip name="СправочникСписокКомандаДобавитьРасширеннаяПодсказка" id="146"/>
									</Button>
									<Button name="СправочникСписокСоздатьСвязь" id="86">
										<Type>CommandBarButton</Type>
										<CommandName>Form.Command.КомандаСоздатьСвязь</CommandName>
										<ExtendedTooltip name="СправочникСписокСоздатьСвязьРасширеннаяПодсказка" id="87"/>
									</Button>
									<Button name="СправочникСписокУдалитьСвязь" id="88">
										<Type>CommandBarButton</Type>
										<CommandName>Form.Command.КомандаУдалитьСвязь</CommandName>
										<ExtendedTooltip name="СправочникСписокУдалитьСвязьРасширеннаяПодсказка" id="89"/>
									</Button>
									<Button name="СправочникСписокКомандаСопоставитьАвтоматически" id="160">
										<Type>CommandBarButton</Type>
										<CommandName>Form.Command.КомандаСопоставитьАвтоматически</CommandName>
										<ExtendedTooltip name="СправочникСписокКомандаСопоставитьАвтоматическиРасширеннаяПодсказка" id="161"/>
									</Button>
								</ChildItems>
							</AutoCommandBar>
							<ExtendedTooltip name="СправочникСписокРасширеннаяПодсказка" id="37"/>
							<SearchStringAddition name="СправочникСписокСтрокаПоиска" id="38">
								<AdditionSource>
									<Item>СправочникСписок</Item>
									<Type>SearchStringRepresentation</Type>
								</AdditionSource>
								<ContextMenu name="СправочникСписокСтрокаПоискаКонтекстноеМеню" id="39"/>
								<ExtendedTooltip name="СправочникСписокСтрокаПоискаРасширеннаяПодсказка" id="40"/>
							</SearchStringAddition>
							<ViewStatusAddition name="СправочникСписокСостояниеПросмотра" id="41">
								<AdditionSource>
									<Item>СправочникСписок</Item>
									<Type>ViewStatusRepresentation</Type>
								</AdditionSource>
								<ContextMenu name="СправочникСписокСостояниеПросмотраКонтекстноеМеню" id="42"/>
								<ExtendedTooltip name="СправочникСписокСостояниеПросмотраРасширеннаяПодсказка" id="43"/>
							</ViewStatusAddition>
							<SearchControlAddition name="СправочникСписокУправлениеПоиском" id="44">
								<AdditionSource>
									<Item>СправочникСписок</Item>
									<Type>SearchControl</Type>
								</AdditionSource>
								<ContextMenu name="СправочникСписокУправлениеПоискомКонтекстноеМеню" id="45"/>
								<ExtendedTooltip name="СправочникСписокУправлениеПоискомРасширеннаяПодсказка" id="46"/>
							</SearchControlAddition>
							<Events>
								<Event name="Selection">СправочникСписокВыбор</Event>
							</Events>
							<ChildItems>
								<LabelField name="СправочникСписокНаименование" id="154">
									<DataPath>СправочникСписок.Наименование</DataPath>
									<ContextMenu name="СправочникСписокНаименованиеКонтекстноеМеню" id="155"/>
									<ExtendedTooltip name="СправочникСписокНаименованиеРасширеннаяПодсказка" id="156"/>
								</LabelField>
								<LabelField name="СправочникСписокИНН" id="157">
									<DataPath>СправочникСписок.ИНН</DataPath>
									<ContextMenu name="СправочникСписокИННКонтекстноеМеню" id="158"/>
									<ExtendedTooltip name="СправочникСписокИННРасширеннаяПодсказка" id="159"/>
								</LabelField>
								<LabelField name="СправочникСписокВетисname" id="90">
									<DataPath>СправочникСписок.Ветисname</DataPath>
									<Width>15</Width>
									<ContextMenu name="СправочникСписокВетисnameКонтекстноеМеню" id="91"/>
									<ExtendedTooltip name="СправочникСписокВетисnameРасширеннаяПодсказка" id="92"/>
								</LabelField>
								<InputField name="СправочникСписокОписание" id="139">
									<DataPath>СправочникСписок.ВетисОписание</DataPath>
									<Visible>false</Visible>
									<ContextMenu name="СправочникСписокОписаниеКонтекстноеМеню" id="140"/>
									<ExtendedTooltip name="СправочникСписокОписаниеРасширеннаяПодсказка" id="141"/>
								</InputField>
							</ChildItems>
						</Table>
					</ChildItems>
				</UsualGroup>
			</ChildItems>
		</UsualGroup>
	</ChildItems>
	<Attributes>
		<Attribute name="Объект" id="1">
			<Type>
				<v8:Type>cfg:DataProcessorObject.ВетисУстановкаСоответствияСправочников</v8:Type>
			</Type>
			<MainAttribute>true</MainAttribute>
		</Attribute>
		<Attribute name="СписокВетис" id="2">
			<Title>
				<v8:item>
					<v8:lang>ru</v8:lang>
					<v8:content>Список ветис</v8:content>
				</v8:item>
			</Title>
			<Type>
				<v8:Type>v8:ValueTable</v8:Type>
			</Type>
			<Columns>
				<Column name="name" id="1">
					<Title>
						<v8:item>
							<v8:lang>ru</v8:lang>
							<v8:content>Name</v8:content>
						</v8:item>
					</Title>
					<Type>
						<v8:Type>xs:string</v8:Type>
						<v8:StringQualifiers>
							<v8:Length>0</v8:Length>
							<v8:AllowedLength>Variable</v8:AllowedLength>
						</v8:StringQualifiers>
					</Type>
				</Column>
				<Column name="type" id="2">
					<Title>
						<v8:item>
							<v8:lang>ru</v8:lang>
							<v8:content>Type</v8:content>
						</v8:item>
					</Title>
					<Type>
						<v8:Type>cfg:EnumRef.ВетисBusinessEntityType</v8:Type>
					</Type>
				</Column>
				<Column name="address" id="3">
					<Title>
						<v8:item>
							<v8:lang>ru</v8:lang>
							<v8:content>Address</v8:content>
						</v8:item>
					</Title>
					<Type>
						<v8:Type>xs:string</v8:Type>
						<v8:StringQualifiers>
							<v8:Length>0</v8:Length>
							<v8:AllowedLength>Variable</v8:AllowedLength>
						</v8:StringQualifiers>
					</Type>
				</Column>
				<Column name="guid" id="5">
					<Title>
						<v8:item>
							<v8:lang>ru</v8:lang>
							<v8:content>Guid</v8:content>
						</v8:item>
					</Title>
					<Type>
						<v8:Type>xs:string</v8:Type>
						<v8:StringQualifiers>
							<v8:Length>0</v8:Length>
							<v8:AllowedLength>Variable</v8:AllowedLength>
						</v8:StringQualifiers>
					</Type>
				</Column>
				<Column name="fullName" id="4">
					<Title>
						<v8:item>
							<v8:lang>ru</v8:lang>
							<v8:content>Full name</v8:content>
						</v8:item>
					</Title>
					<Type>
						<v8:Type>xs:string</v8:Type>
						<v8:StringQualifiers>
							<v8:Length>0</v8:Length>
							<v8:AllowedLength>Variable</v8:AllowedLength>
						</v8:StringQualifiers>
					</Type>
				</Column>
				<Column name="fio" id="6">
					<Title>
						<v8:item>
							<v8:lang>ru</v8:lang>
							<v8:content>Fio</v8:content>
						</v8:item>
					</Title>
					<Type>
						<v8:Type>xs:string</v8:Type>
						<v8:StringQualifiers>
							<v8:Length>0</v8:Length>
							<v8:AllowedLength>Variable</v8:AllowedLength>
						</v8:StringQualifiers>
					</Type>
				</Column>
				<Column name="inn" id="7">
					<Title>
						<v8:item>
							<v8:lang>ru</v8:lang>
							<v8:content>Inn</v8:content>
						</v8:item>
					</Title>
					<Type>
						<v8:Type>xs:string</v8:Type>
						<v8:StringQualifiers>
							<v8:Length>0</v8:Length>
							<v8:AllowedLength>Variable</v8:AllowedLength>
						</v8:StringQualifiers>
					</Type>
				</Column>
			</Columns>
		</Attribute>
		<Attribute name="СправочникСписок" id="3">
			<Title>
				<v8:item>
					<v8:lang>ru</v8:lang>
					<v8:content>Справочник список</v8:content>
				</v8:item>
			</Title>
			<Type>
				<v8:Type>cfg:DynamicList</v8:Type>
			</Type>
			<UseAlways>
				<Field>СправочникСписок.Ссылка</Field>
				<Field>СправочникСписок.Наименование</Field>
				<Field>СправочникСписок.ВетисОписание</Field>
				<Field>СправочникСписок.guid</Field>
				<Field>~СправочникСписок.Ref</Field>
			</UseAlways>
			<Settings xsi:type="DynamicList">
				<ManualQuery>true</ManualQuery>
				<DynamicDataRead>false</DynamicDataRead>
				<QueryText>	ВЫБРАТЬ
	NULL КАК Ссылка,
	NULL КАК Код,
	NULL КАК Наименование,
	NULL КАК ИНН,
	NULL КАК КПП,
	NULL КАК guid,
	NULL КАК Ветисname,
	NULL КАК ВетисОписание
</QueryText>
				<ListSettings>
					<dcsset:filter>
						<dcsset:viewMode>Normal</dcsset:viewMode>
						<dcsset:userSettingID>dfcece9d-5077-440b-b6b3-45a5cb4538eb</dcsset:userSettingID>
					</dcsset:filter>
					<dcsset:order>
						<dcsset:viewMode>Normal</dcsset:viewMode>
						<dcsset:userSettingID>88619765-ccb3-46c6-ac52-38e9c992ebd4</dcsset:userSettingID>
					</dcsset:order>
					<dcsset:conditionalAppearance>
						<dcsset:viewMode>Normal</dcsset:viewMode>
						<dcsset:userSettingID>b75fecce-942b-4aed-abc9-e6a02e460fb3</dcsset:userSettingID>
					</dcsset:conditionalAppearance>
					<dcsset:itemsViewMode>Normal</dcsset:itemsViewMode>
					<dcsset:itemsUserSettingID>911b6018-f537-43e8-a417-da56b22f9aec</dcsset:itemsUserSettingID>
				</ListSettings>
			</Settings>
		</Attribute>
		<Attribute name="ОтборПолноеИмя" id="4">
			<Title>
				<v8:item>
					<v8:lang>ru</v8:lang>
					<v8:content>Полное имя</v8:content>
				</v8:item>
			</Title>
			<Type>
				<v8:Type>xs:string</v8:Type>
				<v8:StringQualifiers>
					<v8:Length>0</v8:Length>
					<v8:AllowedLength>Variable</v8:AllowedLength>
				</v8:StringQualifiers>
			</Type>
			<Save>
				<Field>ОтборПолноеИмя</Field>
			</Save>
		</Attribute>
		<Attribute name="ОтборИНН" id="5">
			<Title>
				<v8:item>
					<v8:lang>ru</v8:lang>
					<v8:content>ИНН</v8:content>
				</v8:item>
			</Title>
			<Type>
				<v8:Type>xs:string</v8:Type>
				<v8:StringQualifiers>
					<v8:Length>0</v8:Length>
					<v8:AllowedLength>Variable</v8:AllowedLength>
				</v8:StringQualifiers>
			</Type>
			<Save>
				<Field>ОтборИНН</Field>
			</Save>
		</Attribute>
		<Attribute name="ОтборGuid" id="6">
			<Title>
				<v8:item>
					<v8:lang>ru</v8:lang>
					<v8:content>guid</v8:content>
				</v8:item>
			</Title>
			<Type>
				<v8:Type>xs:string</v8:Type>
				<v8:StringQualifiers>
					<v8:Length>0</v8:Length>
					<v8:AllowedLength>Variable</v8:AllowedLength>
				</v8:StringQualifiers>
			</Type>
			<Save>
				<Field>ОтборGuid</Field>
			</Save>
		</Attribute>
		<Attribute name="МаксимальноеКоличество" id="7">
			<Title>
				<v8:item>
					<v8:lang>ru</v8:lang>
					<v8:content>Макс.</v8:content>
				</v8:item>
			</Title>
			<Type>
				<v8:Type>xs:decimal</v8:Type>
				<v8:NumberQualifiers>
					<v8:Digits>10</v8:Digits>
					<v8:FractionDigits>0</v8:FractionDigits>
					<v8:AllowedSign>Nonnegative</v8:AllowedSign>
				</v8:NumberQualifiers>
			</Type>
			<Save>
				<Field>МаксимальноеКоличество</Field>
			</Save>
		</Attribute>
		<Attribute name="ОтборФИО" id="8">
			<Title>
				<v8:item>
					<v8:lang>ru</v8:lang>
					<v8:content>ФИО</v8:content>
				</v8:item>
			</Title>
			<Type>
				<v8:Type>xs:string</v8:Type>
				<v8:StringQualifiers>
					<v8:Length>0</v8:Length>
					<v8:AllowedLength>Variable</v8:AllowedLength>
				</v8:StringQualifiers>
			</Type>
			<Save>
				<Field>ОтборФИО</Field>
			</Save>
		</Attribute>
		<Attribute name="ОтборИмя" id="9">
			<Title>
				<v8:item>
					<v8:lang>ru</v8:lang>
					<v8:content>Имя</v8:content>
				</v8:item>
			</Title>
			<Type>
				<v8:Type>xs:string</v8:Type>
				<v8:StringQualifiers>
					<v8:Length>0</v8:Length>
					<v8:AllowedLength>Variable</v8:AllowedLength>
				</v8:StringQualifiers>
			</Type>
			<Save>
				<Field>ОтборИмя</Field>
			</Save>
		</Attribute>
		<Attribute name="ОтборGuidИспользование" id="10">
			<Title>
				<v8:item>
					<v8:lang>ru</v8:lang>
					<v8:content>Отбор guid</v8:content>
				</v8:item>
			</Title>
			<Type>
				<v8:Type>xs:boolean</v8:Type>
			</Type>
			<Save>
				<Field>ОтборGuidИспользование</Field>
			</Save>
		</Attribute>
		<Attribute name="ОтборИмяИспользование" id="11">
			<Title>
				<v8:item>
					<v8:lang>ru</v8:lang>
					<v8:content>Имя</v8:content>
				</v8:item>
			</Title>
			<Type>
				<v8:Type>xs:boolean</v8:Type>
			</Type>
			<Save>
				<Field>ОтборИмяИспользование</Field>
			</Save>
		</Attribute>
		<Attribute name="ОтборИННИспользование" id="12">
			<Title>
				<v8:item>
					<v8:lang>ru</v8:lang>
					<v8:content>ИНН</v8:content>
				</v8:item>
			</Title>
			<Type>
				<v8:Type>xs:boolean</v8:Type>
			</Type>
			<Save>
				<Field>ОтборИННИспользование</Field>
			</Save>
		</Attribute>
		<Attribute name="ОтборПолноеИмяИспользование" id="13">
			<Title>
				<v8:item>
					<v8:lang>ru</v8:lang>
					<v8:content>Полное имя</v8:content>
				</v8:item>
			</Title>
			<Type>
				<v8:Type>xs:boolean</v8:Type>
			</Type>
			<Save>
				<Field>ОтборПолноеИмяИспользование</Field>
			</Save>
		</Attribute>
		<Attribute name="ОтборРегион" id="14">
			<Title>
				<v8:item>
					<v8:lang>ru</v8:lang>
					<v8:content>Регион</v8:content>
				</v8:item>
			</Title>
			<Type>
				<v8:TypeSet>cfg:DefinedType.ВетисRegion</v8:TypeSet>
			</Type>
			<Save>
				<Field>ОтборРегион</Field>
			</Save>
		</Attribute>
		<Attribute name="ОтборРегионИспользование" id="15">
			<Title>
				<v8:item>
					<v8:lang>ru</v8:lang>
					<v8:content>Отбор регион</v8:content>
				</v8:item>
			</Title>
			<Type>
				<v8:Type>xs:boolean</v8:Type>
			</Type>
			<Save>
				<Field>ОтборРегионИспользование</Field>
			</Save>
		</Attribute>
		<Attribute name="ОтборФИОИспользование" id="16">
			<Title>
				<v8:item>
					<v8:lang>ru</v8:lang>
					<v8:content>ФИО</v8:content>
				</v8:item>
			</Title>
			<Type>
				<v8:Type>xs:boolean</v8:Type>
			</Type>
			<Save>
				<Field>ОтборФИОИспользование</Field>
			</Save>
		</Attribute>
		<Attribute name="ОтборРайон" id="17">
			<Title>
				<v8:item>
					<v8:lang>ru</v8:lang>
					<v8:content>Район</v8:content>
				</v8:item>
			</Title>
			<Type>
				<v8:TypeSet>cfg:DefinedType.ВетисDistrict</v8:TypeSet>
			</Type>
			<Save>
				<Field>ОтборРайон</Field>
			</Save>
		</Attribute>
		<Attribute name="ОтборРайонИспользование" id="18">
			<Title>
				<v8:item>
					<v8:lang>ru</v8:lang>
					<v8:content>Район</v8:content>
				</v8:item>
			</Title>
			<Type>
				<v8:Type>xs:boolean</v8:Type>
			</Type>
			<Save>
				<Field>ОтборРайонИспользование</Field>
			</Save>
		</Attribute>
		<ConditionalAppearance>
			<dcsset:item>
				<dcsset:selection>
					<dcsset:item>
						<dcsset:field>СправочникСписокНаименование</dcsset:field>
					</dcsset:item>
					<dcsset:item>
						<dcsset:field>СправочникСписокВетисname</dcsset:field>
					</dcsset:item>
					<dcsset:item>
						<dcsset:field>СправочникСписокИНН</dcsset:field>
					</dcsset:item>
					<dcsset:item>
						<dcsset:field>СправочникСписокОписание</dcsset:field>
					</dcsset:item>
				</dcsset:selection>
				<dcsset:filter>
					<dcsset:item xsi:type="dcsset:FilterItemComparison">
						<dcsset:left xsi:type="dcscor:Field">СправочникСписок.guid</dcsset:left>
						<dcsset:comparisonType>Filled</dcsset:comparisonType>
					</dcsset:item>
				</dcsset:filter>
				<dcsset:appearance>
					<dcscor:item xsi:type="dcsset:SettingsParameterValue">
						<dcscor:parameter>ЦветФона</dcscor:parameter>
						<dcscor:value xsi:type="v8ui:Color">#CCFFCC</dcscor:value>
					</dcscor:item>
				</dcsset:appearance>
			</dcsset:item>
		</ConditionalAppearance>
	</Attributes>
	<Commands>
		<Command name="КомандаНайти" id="1">
			<Title>
				<v8:item>
					<v8:lang>ru</v8:lang>
					<v8:content>Найти</v8:content>
				</v8:item>
			</Title>
			<ToolTip>
				<v8:item>
					<v8:lang>ru</v8:lang>
					<v8:content>Найти по имени</v8:content>
				</v8:item>
			</ToolTip>
			<Picture>
				<xr:Ref>StdPicture.Find</xr:Ref>
				<xr:LoadTransparent>true</xr:LoadTransparent>
			</Picture>
			<Action>КомандаНайти</Action>
			<Representation>Picture</Representation>
		</Command>
		<Command name="КомандаСоздатьСвязь" id="2">
			<Title>
				<v8:item>
					<v8:lang>ru</v8:lang>
					<v8:content>Создать связь</v8:content>
				</v8:item>
			</Title>
			<ToolTip>
				<v8:item>
					<v8:lang>ru</v8:lang>
					<v8:content>Создать связь</v8:content>
				</v8:item>
			</ToolTip>
			<Action>КомандаСоздатьСвязь</Action>
		</Command>
		<Command name="КомандаУдалитьСвязь" id="3">
			<Title>
				<v8:item>
					<v8:lang>ru</v8:lang>
					<v8:content>Удалить связь</v8:content>
				</v8:item>
			</Title>
			<ToolTip>
				<v8:item>
					<v8:lang>ru</v8:lang>
					<v8:content>Удалить связь</v8:content>
				</v8:item>
			</ToolTip>
			<Action>КомандаУдалитьСвязь</Action>
		</Command>
		<Command name="КомандаСправочникДобавить" id="5">
			<Title>
				<v8:item>
					<v8:lang>ru</v8:lang>
					<v8:content>Добавить</v8:content>
				</v8:item>
			</Title>
			<ToolTip>
				<v8:item>
					<v8:lang>ru</v8:lang>
					<v8:content>Добавить</v8:content>
				</v8:item>
			</ToolTip>
			<Action>КомандаСправочникДобавить</Action>
		</Command>
		<Command name="КомандаНайтиПоGuid" id="6">
			<Title>
				<v8:item>
					<v8:lang>ru</v8:lang>
					<v8:content>Найти</v8:content>
				</v8:item>
			</Title>
			<ToolTip>
				<v8:item>
					<v8:lang>ru</v8:lang>
					<v8:content>Найти по guid</v8:content>
				</v8:item>
			</ToolTip>
			<Picture>
				<xr:Ref>StdPicture.Find</xr:Ref>
				<xr:LoadTransparent>true</xr:LoadTransparent>
			</Picture>
			<Action>КомандаНайтиПоGuid</Action>
			<Representation>Picture</Representation>
		</Command>
		<Command name="КомандаСопоставитьАвтоматически" id="7">
			<Title>
				<v8:item>
					<v8:lang>ru</v8:lang>
					<v8:content>Сопоставить автоматически</v8:content>
				</v8:item>
			</Title>
			<ToolTip>
				<v8:item>
					<v8:lang>ru</v8:lang>
					<v8:content>Сопоставить автоматически</v8:content>
				</v8:item>
			</ToolTip>
			<Action>КомандаСопоставитьАвтоматически</Action>
		</Command>
	</Commands>
</Form>