<?xml version="1.0" encoding="UTF-8"?>
<MetaDataObject xmlns="http://v8.1c.ru/8.3/MDClasses" xmlns:app="http://v8.1c.ru/8.2/managed-application/core" xmlns:cfg="http://v8.1c.ru/8.1/data/enterprise/current-config" xmlns:cmi="http://v8.1c.ru/8.2/managed-application/cmi" xmlns:ent="http://v8.1c.ru/8.1/data/enterprise" xmlns:lf="http://v8.1c.ru/8.2/managed-application/logform" xmlns:style="http://v8.1c.ru/8.1/data/ui/style" xmlns:sys="http://v8.1c.ru/8.1/data/ui/fonts/system" xmlns:v8="http://v8.1c.ru/8.1/data/core" xmlns:v8ui="http://v8.1c.ru/8.1/data/ui" xmlns:web="http://v8.1c.ru/8.1/data/ui/colors/web" xmlns:win="http://v8.1c.ru/8.1/data/ui/colors/windows" xmlns:xen="http://v8.1c.ru/8.3/xcf/enums" xmlns:xpr="http://v8.1c.ru/8.3/xcf/predef" xmlns:xr="http://v8.1c.ru/8.3/xcf/readable" xmlns:xs="http://www.w3.org/2001/XMLSchema" xmlns:xsi="http://www.w3.org/2001/XMLSchema-instance" version="2.4">
	<Document uuid="9b079be8-ac62-46cb-82d2-db70f69b53d7">
		<InternalInfo>
			<xr:GeneratedType name="DocumentObject.ВетисТранспортнаяПартия" category="Object">
				<xr:TypeId>63e200c0-0266-4739-9367-5c695beeb5e8</xr:TypeId>
				<xr:ValueId>b93d507f-37be-4013-bd5d-3c3bcfbcfdab</xr:ValueId>
			</xr:GeneratedType>
			<xr:GeneratedType name="DocumentRef.ВетисТранспортнаяПартия" category="Ref">
				<xr:TypeId>07209127-d6f7-47ed-a22b-f4985e3fcf87</xr:TypeId>
				<xr:ValueId>96ca669d-ad79-4b80-b836-e91642186c09</xr:ValueId>
			</xr:GeneratedType>
			<xr:GeneratedType name="DocumentSelection.ВетисТранспортнаяПартия" category="Selection">
				<xr:TypeId>2d7a8f5d-038d-44ad-b235-898060766532</xr:TypeId>
				<xr:ValueId>9fbfbdbe-0465-4c53-b099-26b53e987ddc</xr:ValueId>
			</xr:GeneratedType>
			<xr:GeneratedType name="DocumentList.ВетисТранспортнаяПартия" category="List">
				<xr:TypeId>b743d3ee-3873-4094-a8b7-eef269cc5237</xr:TypeId>
				<xr:ValueId>cc9dc30b-ce2a-498a-9626-e13b583e6118</xr:ValueId>
			</xr:GeneratedType>
			<xr:GeneratedType name="DocumentManager.ВетисТранспортнаяПартия" category="Manager">
				<xr:TypeId>bbd82a96-ba5e-4376-a899-5bb261b19d07</xr:TypeId>
				<xr:ValueId>5e221159-a54f-4449-a0fd-95d3fc7545b7</xr:ValueId>
			</xr:GeneratedType>
		</InternalInfo>
		<Properties>
			<Name>ВетисТранспортнаяПартия</Name>
			<Synonym>
				<v8:item>
					<v8:lang>ru</v8:lang>
					<v8:content>Транспортная партия (ветис)</v8:content>
				</v8:item>
			</Synonym>
			<Comment/>
			<UseStandardCommands>false</UseStandardCommands>
			<Numerator/>
			<NumberType>String</NumberType>
			<NumberLength>11</NumberLength>
			<NumberAllowedLength>Variable</NumberAllowedLength>
			<NumberPeriodicity>Year</NumberPeriodicity>
			<CheckUnique>true</CheckUnique>
			<Autonumbering>true</Autonumbering>
			<StandardAttributes>
				<xr:StandardAttribute name="Posted">
					<xr:LinkByType/>
					<xr:FillChecking>DontCheck</xr:FillChecking>
					<xr:MultiLine>false</xr:MultiLine>
					<xr:FillFromFillingValue>false</xr:FillFromFillingValue>
					<xr:CreateOnInput>Auto</xr:CreateOnInput>
					<xr:MaxValue xsi:nil="true"/>
					<xr:ToolTip/>
					<xr:ExtendedEdit>false</xr:ExtendedEdit>
					<xr:Format/>
					<xr:ChoiceForm/>
					<xr:QuickChoice>Auto</xr:QuickChoice>
					<xr:ChoiceHistoryOnInput>Auto</xr:ChoiceHistoryOnInput>
					<xr:EditFormat/>
					<xr:PasswordMode>false</xr:PasswordMode>
					<xr:MarkNegatives>false</xr:MarkNegatives>
					<xr:MinValue xsi:nil="true"/>
					<xr:Synonym/>
					<xr:Comment/>
					<xr:FullTextSearch>Use</xr:FullTextSearch>
					<xr:ChoiceParameterLinks/>
					<xr:FillValue xsi:nil="true"/>
					<xr:Mask/>
					<xr:ChoiceParameters/>
				</xr:StandardAttribute>
				<xr:StandardAttribute name="Ref">
					<xr:LinkByType/>
					<xr:FillChecking>DontCheck</xr:FillChecking>
					<xr:MultiLine>false</xr:MultiLine>
					<xr:FillFromFillingValue>false</xr:FillFromFillingValue>
					<xr:CreateOnInput>Auto</xr:CreateOnInput>
					<xr:MaxValue xsi:nil="true"/>
					<xr:ToolTip/>
					<xr:ExtendedEdit>false</xr:ExtendedEdit>
					<xr:Format/>
					<xr:ChoiceForm/>
					<xr:QuickChoice>Auto</xr:QuickChoice>
					<xr:ChoiceHistoryOnInput>Auto</xr:ChoiceHistoryOnInput>
					<xr:EditFormat/>
					<xr:PasswordMode>false</xr:PasswordMode>
					<xr:MarkNegatives>false</xr:MarkNegatives>
					<xr:MinValue xsi:nil="true"/>
					<xr:Synonym/>
					<xr:Comment/>
					<xr:FullTextSearch>Use</xr:FullTextSearch>
					<xr:ChoiceParameterLinks/>
					<xr:FillValue xsi:nil="true"/>
					<xr:Mask/>
					<xr:ChoiceParameters/>
				</xr:StandardAttribute>
				<xr:StandardAttribute name="DeletionMark">
					<xr:LinkByType/>
					<xr:FillChecking>DontCheck</xr:FillChecking>
					<xr:MultiLine>false</xr:MultiLine>
					<xr:FillFromFillingValue>false</xr:FillFromFillingValue>
					<xr:CreateOnInput>Auto</xr:CreateOnInput>
					<xr:MaxValue xsi:nil="true"/>
					<xr:ToolTip/>
					<xr:ExtendedEdit>false</xr:ExtendedEdit>
					<xr:Format/>
					<xr:ChoiceForm/>
					<xr:QuickChoice>Auto</xr:QuickChoice>
					<xr:ChoiceHistoryOnInput>Auto</xr:ChoiceHistoryOnInput>
					<xr:EditFormat/>
					<xr:PasswordMode>false</xr:PasswordMode>
					<xr:MarkNegatives>false</xr:MarkNegatives>
					<xr:MinValue xsi:nil="true"/>
					<xr:Synonym/>
					<xr:Comment/>
					<xr:FullTextSearch>Use</xr:FullTextSearch>
					<xr:ChoiceParameterLinks/>
					<xr:FillValue xsi:nil="true"/>
					<xr:Mask/>
					<xr:ChoiceParameters/>
				</xr:StandardAttribute>
				<xr:StandardAttribute name="Date">
					<xr:LinkByType/>
					<xr:FillChecking>ShowError</xr:FillChecking>
					<xr:MultiLine>false</xr:MultiLine>
					<xr:FillFromFillingValue>false</xr:FillFromFillingValue>
					<xr:CreateOnInput>Auto</xr:CreateOnInput>
					<xr:MaxValue xsi:nil="true"/>
					<xr:ToolTip/>
					<xr:ExtendedEdit>false</xr:ExtendedEdit>
					<xr:Format/>
					<xr:ChoiceForm/>
					<xr:QuickChoice>Auto</xr:QuickChoice>
					<xr:ChoiceHistoryOnInput>Auto</xr:ChoiceHistoryOnInput>
					<xr:EditFormat/>
					<xr:PasswordMode>false</xr:PasswordMode>
					<xr:MarkNegatives>false</xr:MarkNegatives>
					<xr:MinValue xsi:nil="true"/>
					<xr:Synonym/>
					<xr:Comment/>
					<xr:FullTextSearch>Use</xr:FullTextSearch>
					<xr:ChoiceParameterLinks/>
					<xr:FillValue xsi:nil="true"/>
					<xr:Mask/>
					<xr:ChoiceParameters/>
				</xr:StandardAttribute>
				<xr:StandardAttribute name="Number">
					<xr:LinkByType/>
					<xr:FillChecking>DontCheck</xr:FillChecking>
					<xr:MultiLine>false</xr:MultiLine>
					<xr:FillFromFillingValue>false</xr:FillFromFillingValue>
					<xr:CreateOnInput>Auto</xr:CreateOnInput>
					<xr:MaxValue xsi:nil="true"/>
					<xr:ToolTip/>
					<xr:ExtendedEdit>false</xr:ExtendedEdit>
					<xr:Format/>
					<xr:ChoiceForm/>
					<xr:QuickChoice>Auto</xr:QuickChoice>
					<xr:ChoiceHistoryOnInput>Auto</xr:ChoiceHistoryOnInput>
					<xr:EditFormat/>
					<xr:PasswordMode>false</xr:PasswordMode>
					<xr:MarkNegatives>false</xr:MarkNegatives>
					<xr:MinValue xsi:nil="true"/>
					<xr:Synonym/>
					<xr:Comment/>
					<xr:FullTextSearch>Use</xr:FullTextSearch>
					<xr:ChoiceParameterLinks/>
					<xr:FillValue xsi:nil="true"/>
					<xr:Mask/>
					<xr:ChoiceParameters/>
				</xr:StandardAttribute>
			</StandardAttributes>
			<Characteristics/>
			<BasedOn/>
			<InputByString>
				<xr:Field>Document.ВетисТранспортнаяПартия.StandardAttribute.Number</xr:Field>
			</InputByString>
			<CreateOnInput>Use</CreateOnInput>
			<SearchStringModeOnInputByString>Begin</SearchStringModeOnInputByString>
			<FullTextSearchOnInputByString>DontUse</FullTextSearchOnInputByString>
			<ChoiceDataGetModeOnInputByString>Directly</ChoiceDataGetModeOnInputByString>
			<DefaultObjectForm>Document.ВетисТранспортнаяПартия.Form.ФормаДокумента</DefaultObjectForm>
			<DefaultListForm/>
			<DefaultChoiceForm/>
			<AuxiliaryObjectForm/>
			<AuxiliaryListForm/>
			<AuxiliaryChoiceForm/>
			<Posting>Allow</Posting>
			<RealTimePosting>Allow</RealTimePosting>
			<RegisterRecordsDeletion>AutoDeleteOnUnpost</RegisterRecordsDeletion>
			<RegisterRecordsWritingOnPost>WriteSelected</RegisterRecordsWritingOnPost>
			<SequenceFilling>AutoFill</SequenceFilling>
			<RegisterRecords>
				<xr:Item xsi:type="xr:MDObjectRef">AccumulationRegister.ВетисСкладскойЖурнал</xr:Item>
			</RegisterRecords>
			<PostInPrivilegedMode>false</PostInPrivilegedMode>
			<UnpostInPrivilegedMode>false</UnpostInPrivilegedMode>
			<IncludeHelpInContents>false</IncludeHelpInContents>
			<DataLockFields/>
			<DataLockControlMode>Automatic</DataLockControlMode>
			<FullTextSearch>Use</FullTextSearch>
			<ObjectPresentation/>
			<ExtendedObjectPresentation/>
			<ListPresentation/>
			<ExtendedListPresentation/>
			<Explanation/>
			<ChoiceHistoryOnInput>Auto</ChoiceHistoryOnInput>
		</Properties>
		<ChildObjects>
			<Attribute uuid="f6297e1e-d193-41ee-875e-8e6a4335f932">
				<Properties>
					<Name>ДокументОснование</Name>
					<Synonym>
						<v8:item>
							<v8:lang>ru</v8:lang>
							<v8:content>Документ основание</v8:content>
						</v8:item>
					</Synonym>
					<Comment/>
					<Type>
						<v8:TypeSet>cfg:DocumentRef</v8:TypeSet>
					</Type>
					<PasswordMode>false</PasswordMode>
					<Format/>
					<EditFormat/>
					<ToolTip/>
					<MarkNegatives>false</MarkNegatives>
					<Mask/>
					<MultiLine>false</MultiLine>
					<ExtendedEdit>false</ExtendedEdit>
					<MinValue xsi:nil="true"/>
					<MaxValue xsi:nil="true"/>
					<FillFromFillingValue>false</FillFromFillingValue>
					<FillValue xsi:nil="true"/>
					<FillChecking>DontCheck</FillChecking>
					<ChoiceFoldersAndItems>Items</ChoiceFoldersAndItems>
					<ChoiceParameterLinks/>
					<ChoiceParameters/>
					<QuickChoice>Auto</QuickChoice>
					<CreateOnInput>Auto</CreateOnInput>
					<ChoiceForm/>
					<LinkByType/>
					<ChoiceHistoryOnInput>Auto</ChoiceHistoryOnInput>
					<Indexing>DontIndex</Indexing>
					<FullTextSearch>Use</FullTextSearch>
				</Properties>
			</Attribute>
			<Attribute uuid="91ef872f-2bd1-43fc-b5ca-ea0ff94dcc97">
				<Properties>
					<Name>Отправитель</Name>
					<Synonym>
						<v8:item>
							<v8:lang>ru</v8:lang>
							<v8:content>Отправитель</v8:content>
						</v8:item>
					</Synonym>
					<Comment/>
					<Type>
						<v8:TypeSet>cfg:DefinedType.ВетисBusinessEntity</v8:TypeSet>
					</Type>
					<PasswordMode>false</PasswordMode>
					<Format/>
					<EditFormat/>
					<ToolTip/>
					<MarkNegatives>false</MarkNegatives>
					<Mask/>
					<MultiLine>false</MultiLine>
					<ExtendedEdit>false</ExtendedEdit>
					<MinValue xsi:nil="true"/>
					<MaxValue xsi:nil="true"/>
					<FillFromFillingValue>false</FillFromFillingValue>
					<FillValue xsi:nil="true"/>
					<FillChecking>DontCheck</FillChecking>
					<ChoiceFoldersAndItems>Items</ChoiceFoldersAndItems>
					<ChoiceParameterLinks/>
					<ChoiceParameters/>
					<QuickChoice>Auto</QuickChoice>
					<CreateOnInput>Auto</CreateOnInput>
					<ChoiceForm/>
					<LinkByType/>
					<ChoiceHistoryOnInput>Auto</ChoiceHistoryOnInput>
					<Indexing>Index</Indexing>
					<FullTextSearch>Use</FullTextSearch>
				</Properties>
			</Attribute>
			<Attribute uuid="757d42ec-9f8f-40d7-8e41-779589ec0da1">
				<Properties>
					<Name>ОтправительПредприятие</Name>
					<Synonym>
						<v8:item>
							<v8:lang>ru</v8:lang>
							<v8:content>Предприятие</v8:content>
						</v8:item>
					</Synonym>
					<Comment/>
					<Type>
						<v8:TypeSet>cfg:DefinedType.ВетисEnterprise</v8:TypeSet>
					</Type>
					<PasswordMode>false</PasswordMode>
					<Format/>
					<EditFormat/>
					<ToolTip/>
					<MarkNegatives>false</MarkNegatives>
					<Mask/>
					<MultiLine>false</MultiLine>
					<ExtendedEdit>false</ExtendedEdit>
					<MinValue xsi:nil="true"/>
					<MaxValue xsi:nil="true"/>
					<FillFromFillingValue>false</FillFromFillingValue>
					<FillValue xsi:nil="true"/>
					<FillChecking>DontCheck</FillChecking>
					<ChoiceFoldersAndItems>FoldersAndItems</ChoiceFoldersAndItems>
					<ChoiceParameterLinks>
						<xr:Link>
							<xr:Name>Отбор.Владелец</xr:Name>
							<xr:DataPath xsi:type="xs:string">Document.ВетисТранспортнаяПартия.Attribute.Отправитель</xr:DataPath>
							<xr:ValueChange>Clear</xr:ValueChange>
						</xr:Link>
					</ChoiceParameterLinks>
					<ChoiceParameters/>
					<QuickChoice>Auto</QuickChoice>
					<CreateOnInput>Auto</CreateOnInput>
					<ChoiceForm/>
					<LinkByType/>
					<ChoiceHistoryOnInput>Auto</ChoiceHistoryOnInput>
					<Indexing>DontIndex</Indexing>
					<FullTextSearch>Use</FullTextSearch>
				</Properties>
			</Attribute>
			<Attribute uuid="e7fe166c-ee34-45eb-8eaf-329ff4c750ec">
				<Properties>
					<Name>Получатель</Name>
					<Synonym>
						<v8:item>
							<v8:lang>ru</v8:lang>
							<v8:content>Получатель</v8:content>
						</v8:item>
					</Synonym>
					<Comment/>
					<Type>
						<v8:TypeSet>cfg:DefinedType.ВетисBusinessEntity</v8:TypeSet>
					</Type>
					<PasswordMode>false</PasswordMode>
					<Format/>
					<EditFormat/>
					<ToolTip/>
					<MarkNegatives>false</MarkNegatives>
					<Mask/>
					<MultiLine>false</MultiLine>
					<ExtendedEdit>false</ExtendedEdit>
					<MinValue xsi:nil="true"/>
					<MaxValue xsi:nil="true"/>
					<FillFromFillingValue>false</FillFromFillingValue>
					<FillValue xsi:nil="true"/>
					<FillChecking>DontCheck</FillChecking>
					<ChoiceFoldersAndItems>Items</ChoiceFoldersAndItems>
					<ChoiceParameterLinks/>
					<ChoiceParameters/>
					<QuickChoice>Auto</QuickChoice>
					<CreateOnInput>Auto</CreateOnInput>
					<ChoiceForm/>
					<LinkByType/>
					<ChoiceHistoryOnInput>Auto</ChoiceHistoryOnInput>
					<Indexing>Index</Indexing>
					<FullTextSearch>Use</FullTextSearch>
				</Properties>
			</Attribute>
			<Attribute uuid="e24101aa-c5fd-403a-b14b-20031dbf30fe">
				<Properties>
					<Name>ПолучательПредприятие</Name>
					<Synonym>
						<v8:item>
							<v8:lang>ru</v8:lang>
							<v8:content>Предприятие</v8:content>
						</v8:item>
					</Synonym>
					<Comment/>
					<Type>
						<v8:TypeSet>cfg:DefinedType.ВетисEnterprise</v8:TypeSet>
					</Type>
					<PasswordMode>false</PasswordMode>
					<Format/>
					<EditFormat/>
					<ToolTip/>
					<MarkNegatives>false</MarkNegatives>
					<Mask/>
					<MultiLine>false</MultiLine>
					<ExtendedEdit>false</ExtendedEdit>
					<MinValue xsi:nil="true"/>
					<MaxValue xsi:nil="true"/>
					<FillFromFillingValue>false</FillFromFillingValue>
					<FillValue xsi:nil="true"/>
					<FillChecking>DontCheck</FillChecking>
					<ChoiceFoldersAndItems>Items</ChoiceFoldersAndItems>
					<ChoiceParameterLinks>
						<xr:Link>
							<xr:Name>Отбор.Владелец</xr:Name>
							<xr:DataPath xsi:type="xs:string">Document.ВетисТранспортнаяПартия.Attribute.Получатель</xr:DataPath>
							<xr:ValueChange>Clear</xr:ValueChange>
						</xr:Link>
					</ChoiceParameterLinks>
					<ChoiceParameters/>
					<QuickChoice>Auto</QuickChoice>
					<CreateOnInput>Auto</CreateOnInput>
					<ChoiceForm/>
					<LinkByType/>
					<ChoiceHistoryOnInput>Auto</ChoiceHistoryOnInput>
					<Indexing>DontIndex</Indexing>
					<FullTextSearch>Use</FullTextSearch>
				</Properties>
			</Attribute>
			<Attribute uuid="3290cfd6-18b2-4374-a325-798f4acfe3c8">
				<Properties>
					<Name>Транспорт</Name>
					<Synonym>
						<v8:item>
							<v8:lang>ru</v8:lang>
							<v8:content>Транспорт</v8:content>
						</v8:item>
					</Synonym>
					<Comment/>
					<Type>
						<v8:TypeSet>cfg:DefinedType.ВетисTransport</v8:TypeSet>
					</Type>
					<PasswordMode>false</PasswordMode>
					<Format/>
					<EditFormat/>
					<ToolTip/>
					<MarkNegatives>false</MarkNegatives>
					<Mask/>
					<MultiLine>false</MultiLine>
					<ExtendedEdit>false</ExtendedEdit>
					<MinValue xsi:nil="true"/>
					<MaxValue xsi:nil="true"/>
					<FillFromFillingValue>false</FillFromFillingValue>
					<FillValue xsi:nil="true"/>
					<FillChecking>DontCheck</FillChecking>
					<ChoiceFoldersAndItems>Items</ChoiceFoldersAndItems>
					<ChoiceParameterLinks>
						<xr:Link>
							<xr:Name>Отбор.ВладелецТС</xr:Name>
							<xr:DataPath xsi:type="xs:string">0</xr:DataPath>
							<xr:ValueChange>Clear</xr:ValueChange>
						</xr:Link>
					</ChoiceParameterLinks>
					<ChoiceParameters/>
					<QuickChoice>Auto</QuickChoice>
					<CreateOnInput>Auto</CreateOnInput>
					<ChoiceForm/>
					<LinkByType/>
					<ChoiceHistoryOnInput>Auto</ChoiceHistoryOnInput>
					<Indexing>DontIndex</Indexing>
					<FullTextSearch>Use</FullTextSearch>
				</Properties>
			</Attribute>
			<Attribute uuid="b5d5c7ce-114c-4895-a670-56ff9a3b9529">
				<Properties>
					<Name>СпособХраненияПродукции</Name>
					<Synonym>
						<v8:item>
							<v8:lang>ru</v8:lang>
							<v8:content>Способ хранения продукции</v8:content>
						</v8:item>
					</Synonym>
					<Comment/>
					<Type>
						<v8:Type>cfg:EnumRef.ВетисTransportStorageType</v8:Type>
					</Type>
					<PasswordMode>false</PasswordMode>
					<Format/>
					<EditFormat/>
					<ToolTip/>
					<MarkNegatives>false</MarkNegatives>
					<Mask/>
					<MultiLine>false</MultiLine>
					<ExtendedEdit>false</ExtendedEdit>
					<MinValue xsi:nil="true"/>
					<MaxValue xsi:nil="true"/>
					<FillFromFillingValue>false</FillFromFillingValue>
					<FillValue xsi:nil="true"/>
					<FillChecking>DontCheck</FillChecking>
					<ChoiceFoldersAndItems>Items</ChoiceFoldersAndItems>
					<ChoiceParameterLinks/>
					<ChoiceParameters/>
					<QuickChoice>Auto</QuickChoice>
					<CreateOnInput>Auto</CreateOnInput>
					<ChoiceForm/>
					<LinkByType/>
					<ChoiceHistoryOnInput>Auto</ChoiceHistoryOnInput>
					<Indexing>DontIndex</Indexing>
					<FullTextSearch>Use</FullTextSearch>
				</Properties>
			</Attribute>
			<Attribute uuid="8c4322e2-451e-478a-a22c-329059f55727">
				<Properties>
					<Name>Подразделение</Name>
					<Synonym>
						<v8:item>
							<v8:lang>ru</v8:lang>
							<v8:content>Подразделение</v8:content>
						</v8:item>
					</Synonym>
					<Comment/>
					<Type>
						<v8:Type>xs:string</v8:Type>
						<v8:StringQualifiers>
							<v8:Length>10</v8:Length>
							<v8:AllowedLength>Variable</v8:AllowedLength>
						</v8:StringQualifiers>
					</Type>
					<PasswordMode>false</PasswordMode>
					<Format/>
					<EditFormat/>
					<ToolTip/>
					<MarkNegatives>false</MarkNegatives>
					<Mask/>
					<MultiLine>false</MultiLine>
					<ExtendedEdit>false</ExtendedEdit>
					<MinValue xsi:nil="true"/>
					<MaxValue xsi:nil="true"/>
					<FillFromFillingValue>false</FillFromFillingValue>
					<FillValue xsi:nil="true"/>
					<FillChecking>DontCheck</FillChecking>
					<ChoiceFoldersAndItems>Items</ChoiceFoldersAndItems>
					<ChoiceParameterLinks/>
					<ChoiceParameters/>
					<QuickChoice>Auto</QuickChoice>
					<CreateOnInput>Auto</CreateOnInput>
					<ChoiceForm/>
					<LinkByType/>
					<ChoiceHistoryOnInput>Auto</ChoiceHistoryOnInput>
					<Indexing>DontIndex</Indexing>
					<FullTextSearch>Use</FullTextSearch>
				</Properties>
			</Attribute>
			<Attribute uuid="ae8aa6df-e0d4-4fcc-997d-6a9ae32272b5">
				<Properties>
					<Name>Ответственный</Name>
					<Synonym>
						<v8:item>
							<v8:lang>ru</v8:lang>
							<v8:content>Ответственный</v8:content>
						</v8:item>
					</Synonym>
					<Comment/>
					<Type>
						<v8:TypeSet>cfg:DefinedType.ВетисПользователь</v8:TypeSet>
					</Type>
					<PasswordMode>false</PasswordMode>
					<Format/>
					<EditFormat/>
					<ToolTip/>
					<MarkNegatives>false</MarkNegatives>
					<Mask/>
					<MultiLine>false</MultiLine>
					<ExtendedEdit>false</ExtendedEdit>
					<MinValue xsi:nil="true"/>
					<MaxValue xsi:nil="true"/>
					<FillFromFillingValue>false</FillFromFillingValue>
					<FillValue xsi:nil="true"/>
					<FillChecking>DontCheck</FillChecking>
					<ChoiceFoldersAndItems>Items</ChoiceFoldersAndItems>
					<ChoiceParameterLinks/>
					<ChoiceParameters/>
					<QuickChoice>Auto</QuickChoice>
					<CreateOnInput>Auto</CreateOnInput>
					<ChoiceForm/>
					<LinkByType/>
					<ChoiceHistoryOnInput>Auto</ChoiceHistoryOnInput>
					<Indexing>Index</Indexing>
					<FullTextSearch>Use</FullTextSearch>
				</Properties>
			</Attribute>
			<Attribute uuid="1656eba1-d35e-4e9a-9ea1-b75d781359ac">
				<Properties>
					<Name>Комментарий</Name>
					<Synonym>
						<v8:item>
							<v8:lang>ru</v8:lang>
							<v8:content>Комментарий</v8:content>
						</v8:item>
					</Synonym>
					<Comment/>
					<Type>
						<v8:Type>xs:string</v8:Type>
						<v8:StringQualifiers>
							<v8:Length>0</v8:Length>
							<v8:AllowedLength>Variable</v8:AllowedLength>
						</v8:StringQualifiers>
					</Type>
					<PasswordMode>false</PasswordMode>
					<Format/>
					<EditFormat/>
					<ToolTip/>
					<MarkNegatives>false</MarkNegatives>
					<Mask/>
					<MultiLine>false</MultiLine>
					<ExtendedEdit>false</ExtendedEdit>
					<MinValue xsi:nil="true"/>
					<MaxValue xsi:nil="true"/>
					<FillFromFillingValue>false</FillFromFillingValue>
					<FillValue xsi:nil="true"/>
					<FillChecking>DontCheck</FillChecking>
					<ChoiceFoldersAndItems>Items</ChoiceFoldersAndItems>
					<ChoiceParameterLinks/>
					<ChoiceParameters/>
					<QuickChoice>Auto</QuickChoice>
					<CreateOnInput>Auto</CreateOnInput>
					<ChoiceForm/>
					<LinkByType/>
					<ChoiceHistoryOnInput>Auto</ChoiceHistoryOnInput>
					<Indexing>DontIndex</Indexing>
					<FullTextSearch>Use</FullTextSearch>
				</Properties>
			</Attribute>
			<Form>ФормаДокумента</Form>
			<TabularSection uuid="f5f9771c-9962-444b-94a1-a2e72d832ef4">
				<InternalInfo>
					<xr:GeneratedType name="DocumentTabularSection.ВетисТранспортнаяПартия.Товары" category="TabularSection">
						<xr:TypeId>b8e906b8-6077-4d86-9b71-7bfbb17c9604</xr:TypeId>
						<xr:ValueId>e4a2b5ac-45cd-494e-9589-53fbac6f854a</xr:ValueId>
					</xr:GeneratedType>
					<xr:GeneratedType name="DocumentTabularSectionRow.ВетисТранспортнаяПартия.Товары" category="TabularSectionRow">
						<xr:TypeId>a2435119-fc6b-43a3-b995-746076e8995f</xr:TypeId>
						<xr:ValueId>d105d183-2676-4d55-b9da-4b4699a592b8</xr:ValueId>
					</xr:GeneratedType>
				</InternalInfo>
				<Properties>
					<Name>Товары</Name>
					<Synonym>
						<v8:item>
							<v8:lang>ru</v8:lang>
							<v8:content>Товары</v8:content>
						</v8:item>
					</Synonym>
					<Comment/>
					<ToolTip/>
					<FillChecking>DontCheck</FillChecking>
					<StandardAttributes>
						<xr:StandardAttribute name="LineNumber">
							<xr:LinkByType/>
							<xr:FillChecking>DontCheck</xr:FillChecking>
							<xr:MultiLine>false</xr:MultiLine>
							<xr:FillFromFillingValue>false</xr:FillFromFillingValue>
							<xr:CreateOnInput>Auto</xr:CreateOnInput>
							<xr:MaxValue xsi:nil="true"/>
							<xr:ToolTip/>
							<xr:ExtendedEdit>false</xr:ExtendedEdit>
							<xr:Format/>
							<xr:ChoiceForm/>
							<xr:QuickChoice>Auto</xr:QuickChoice>
							<xr:ChoiceHistoryOnInput>Auto</xr:ChoiceHistoryOnInput>
							<xr:EditFormat/>
							<xr:PasswordMode>false</xr:PasswordMode>
							<xr:MarkNegatives>false</xr:MarkNegatives>
							<xr:MinValue xsi:nil="true"/>
							<xr:Synonym/>
							<xr:Comment/>
							<xr:FullTextSearch>Use</xr:FullTextSearch>
							<xr:ChoiceParameterLinks/>
							<xr:FillValue xsi:nil="true"/>
							<xr:Mask/>
							<xr:ChoiceParameters/>
						</xr:StandardAttribute>
					</StandardAttributes>
				</Properties>
				<ChildObjects>
					<Attribute uuid="b1c15a56-25a9-4661-be4c-5f135d86820b">
						<Properties>
							<Name>КлючСтроки</Name>
							<Synonym>
								<v8:item>
									<v8:lang>ru</v8:lang>
									<v8:content>Ключ строки</v8:content>
								</v8:item>
							</Synonym>
							<Comment/>
							<Type>
								<v8:Type>xs:decimal</v8:Type>
								<v8:NumberQualifiers>
									<v8:Digits>5</v8:Digits>
									<v8:FractionDigits>0</v8:FractionDigits>
									<v8:AllowedSign>Nonnegative</v8:AllowedSign>
								</v8:NumberQualifiers>
							</Type>
							<PasswordMode>false</PasswordMode>
							<Format/>
							<EditFormat/>
							<ToolTip/>
							<MarkNegatives>false</MarkNegatives>
							<Mask/>
							<MultiLine>false</MultiLine>
							<ExtendedEdit>false</ExtendedEdit>
							<MinValue xsi:nil="true"/>
							<MaxValue xsi:nil="true"/>
							<FillChecking>DontCheck</FillChecking>
							<ChoiceFoldersAndItems>Items</ChoiceFoldersAndItems>
							<ChoiceParameterLinks/>
							<ChoiceParameters/>
							<QuickChoice>Auto</QuickChoice>
							<CreateOnInput>Auto</CreateOnInput>
							<ChoiceForm/>
							<LinkByType/>
							<ChoiceHistoryOnInput>Auto</ChoiceHistoryOnInput>
							<Indexing>DontIndex</Indexing>
							<FullTextSearch>Use</FullTextSearch>
						</Properties>
					</Attribute>
					<Attribute uuid="1d845e16-59b6-45e7-90c9-38bf9e1cd639">
						<Properties>
							<Name>НоменклатурнаяГруппа</Name>
							<Synonym>
								<v8:item>
									<v8:lang>ru</v8:lang>
									<v8:content>Номенклатурная группа</v8:content>
								</v8:item>
							</Synonym>
							<Comment/>
							<Type>
								<v8:TypeSet>cfg:DefinedType.ВетисSubProduct</v8:TypeSet>
							</Type>
							<PasswordMode>false</PasswordMode>
							<Format/>
							<EditFormat/>
							<ToolTip/>
							<MarkNegatives>false</MarkNegatives>
							<Mask/>
							<MultiLine>false</MultiLine>
							<ExtendedEdit>false</ExtendedEdit>
							<MinValue xsi:nil="true"/>
							<MaxValue xsi:nil="true"/>
							<FillChecking>DontCheck</FillChecking>
							<ChoiceFoldersAndItems>Items</ChoiceFoldersAndItems>
							<ChoiceParameterLinks/>
							<ChoiceParameters/>
							<QuickChoice>Auto</QuickChoice>
							<CreateOnInput>Auto</CreateOnInput>
							<ChoiceForm/>
							<LinkByType/>
							<ChoiceHistoryOnInput>Auto</ChoiceHistoryOnInput>
							<Indexing>DontIndex</Indexing>
							<FullTextSearch>Use</FullTextSearch>
						</Properties>
					</Attribute>
					<Attribute uuid="585aff46-28b9-45cf-bec4-737baf845d64">
						<Properties>
							<Name>Номенклатура</Name>
							<Synonym>
								<v8:item>
									<v8:lang>ru</v8:lang>
									<v8:content>Номенклатура</v8:content>
								</v8:item>
							</Synonym>
							<Comment/>
							<Type>
								<v8:TypeSet>cfg:DefinedType.ВетисProductItem</v8:TypeSet>
							</Type>
							<PasswordMode>false</PasswordMode>
							<Format/>
							<EditFormat/>
							<ToolTip/>
							<MarkNegatives>false</MarkNegatives>
							<Mask/>
							<MultiLine>false</MultiLine>
							<ExtendedEdit>false</ExtendedEdit>
							<MinValue xsi:nil="true"/>
							<MaxValue xsi:nil="true"/>
							<FillChecking>DontCheck</FillChecking>
							<ChoiceFoldersAndItems>Items</ChoiceFoldersAndItems>
							<ChoiceParameterLinks/>
							<ChoiceParameters/>
							<QuickChoice>Auto</QuickChoice>
							<CreateOnInput>Auto</CreateOnInput>
							<ChoiceForm/>
							<LinkByType/>
							<ChoiceHistoryOnInput>Auto</ChoiceHistoryOnInput>
							<Indexing>DontIndex</Indexing>
							<FullTextSearch>Use</FullTextSearch>
						</Properties>
					</Attribute>
					<Attribute uuid="413a8454-5c10-4abd-8ee6-e4e4e76d5180">
						<Properties>
							<Name>Количество</Name>
							<Synonym>
								<v8:item>
									<v8:lang>ru</v8:lang>
									<v8:content>Количество</v8:content>
								</v8:item>
							</Synonym>
							<Comment/>
							<Type>
								<v8:Type>xs:decimal</v8:Type>
								<v8:NumberQualifiers>
									<v8:Digits>15</v8:Digits>
									<v8:FractionDigits>3</v8:FractionDigits>
									<v8:AllowedSign>Any</v8:AllowedSign>
								</v8:NumberQualifiers>
							</Type>
							<PasswordMode>false</PasswordMode>
							<Format/>
							<EditFormat/>
							<ToolTip/>
							<MarkNegatives>false</MarkNegatives>
							<Mask/>
							<MultiLine>false</MultiLine>
							<ExtendedEdit>false</ExtendedEdit>
							<MinValue xsi:nil="true"/>
							<MaxValue xsi:nil="true"/>
							<FillChecking>DontCheck</FillChecking>
							<ChoiceFoldersAndItems>Items</ChoiceFoldersAndItems>
							<ChoiceParameterLinks/>
							<ChoiceParameters/>
							<QuickChoice>Auto</QuickChoice>
							<CreateOnInput>Auto</CreateOnInput>
							<ChoiceForm/>
							<LinkByType/>
							<ChoiceHistoryOnInput>Auto</ChoiceHistoryOnInput>
							<Indexing>DontIndex</Indexing>
							<FullTextSearch>Use</FullTextSearch>
						</Properties>
					</Attribute>
					<Attribute uuid="3e70abdb-c7fc-4709-ad1b-05d72115e30b">
						<Properties>
							<Name>КоличествоМест</Name>
							<Synonym>
								<v8:item>
									<v8:lang>ru</v8:lang>
									<v8:content>Количество мест</v8:content>
								</v8:item>
							</Synonym>
							<Comment/>
							<Type>
								<v8:Type>xs:decimal</v8:Type>
								<v8:NumberQualifiers>
									<v8:Digits>15</v8:Digits>
									<v8:FractionDigits>3</v8:FractionDigits>
									<v8:AllowedSign>Any</v8:AllowedSign>
								</v8:NumberQualifiers>
							</Type>
							<PasswordMode>false</PasswordMode>
							<Format/>
							<EditFormat/>
							<ToolTip/>
							<MarkNegatives>false</MarkNegatives>
							<Mask/>
							<MultiLine>false</MultiLine>
							<ExtendedEdit>false</ExtendedEdit>
							<MinValue xsi:nil="true"/>
							<MaxValue xsi:nil="true"/>
							<FillChecking>DontCheck</FillChecking>
							<ChoiceFoldersAndItems>Items</ChoiceFoldersAndItems>
							<ChoiceParameterLinks/>
							<ChoiceParameters/>
							<QuickChoice>Auto</QuickChoice>
							<CreateOnInput>Auto</CreateOnInput>
							<ChoiceForm/>
							<LinkByType/>
							<ChoiceHistoryOnInput>Auto</ChoiceHistoryOnInput>
							<Indexing>DontIndex</Indexing>
							<FullTextSearch>Use</FullTextSearch>
						</Properties>
					</Attribute>
					<Attribute uuid="49174d3a-6165-463e-bf80-4c47b2bcbc2a">
						<Properties>
							<Name>ЕдиницаИзмерения</Name>
							<Synonym>
								<v8:item>
									<v8:lang>ru</v8:lang>
									<v8:content>Единица измерения</v8:content>
								</v8:item>
							</Synonym>
							<Comment/>
							<Type>
								<v8:TypeSet>cfg:DefinedType.ВетисUnit</v8:TypeSet>
							</Type>
							<PasswordMode>false</PasswordMode>
							<Format/>
							<EditFormat/>
							<ToolTip/>
							<MarkNegatives>false</MarkNegatives>
							<Mask/>
							<MultiLine>false</MultiLine>
							<ExtendedEdit>false</ExtendedEdit>
							<MinValue xsi:nil="true"/>
							<MaxValue xsi:nil="true"/>
							<FillChecking>DontCheck</FillChecking>
							<ChoiceFoldersAndItems>Items</ChoiceFoldersAndItems>
							<ChoiceParameterLinks/>
							<ChoiceParameters/>
							<QuickChoice>Auto</QuickChoice>
							<CreateOnInput>Auto</CreateOnInput>
							<ChoiceForm/>
							<LinkByType/>
							<ChoiceHistoryOnInput>Auto</ChoiceHistoryOnInput>
							<Indexing>DontIndex</Indexing>
							<FullTextSearch>Use</FullTextSearch>
						</Properties>
					</Attribute>
					<Attribute uuid="48594c73-27d0-4278-8dfa-2c2531deff3c">
						<Properties>
							<Name>Упаковка</Name>
							<Synonym>
								<v8:item>
									<v8:lang>ru</v8:lang>
									<v8:content>Упаковка</v8:content>
								</v8:item>
							</Synonym>
							<Comment/>
							<Type>
								<v8:TypeSet>cfg:DefinedType.ВетисPackingForm</v8:TypeSet>
							</Type>
							<PasswordMode>false</PasswordMode>
							<Format/>
							<EditFormat/>
							<ToolTip/>
							<MarkNegatives>false</MarkNegatives>
							<Mask/>
							<MultiLine>false</MultiLine>
							<ExtendedEdit>false</ExtendedEdit>
							<MinValue xsi:nil="true"/>
							<MaxValue xsi:nil="true"/>
							<FillChecking>DontCheck</FillChecking>
							<ChoiceFoldersAndItems>Items</ChoiceFoldersAndItems>
							<ChoiceParameterLinks/>
							<ChoiceParameters/>
							<QuickChoice>Auto</QuickChoice>
							<CreateOnInput>Auto</CreateOnInput>
							<ChoiceForm/>
							<LinkByType/>
							<ChoiceHistoryOnInput>Auto</ChoiceHistoryOnInput>
							<Indexing>DontIndex</Indexing>
							<FullTextSearch>Use</FullTextSearch>
						</Properties>
					</Attribute>
				</ChildObjects>
			</TabularSection>
			<TabularSection uuid="5f55d374-34e1-455b-9c09-39a199fce295">
				<InternalInfo>
					<xr:GeneratedType name="DocumentTabularSection.ВетисТранспортнаяПартия.Партии" category="TabularSection">
						<xr:TypeId>f1d285b3-fa18-4282-9dd1-d51e2c5703a6</xr:TypeId>
						<xr:ValueId>322fdfc7-a3c7-4159-b6f4-8b57cf48b709</xr:ValueId>
					</xr:GeneratedType>
					<xr:GeneratedType name="DocumentTabularSectionRow.ВетисТранспортнаяПартия.Партии" category="TabularSectionRow">
						<xr:TypeId>22dc7bda-8fcb-41ab-8d33-fbd89e87846b</xr:TypeId>
						<xr:ValueId>055795fc-feea-4a8e-b108-6fbe9b1bff57</xr:ValueId>
					</xr:GeneratedType>
				</InternalInfo>
				<Properties>
					<Name>Партии</Name>
					<Synonym>
						<v8:item>
							<v8:lang>ru</v8:lang>
							<v8:content>Партии</v8:content>
						</v8:item>
					</Synonym>
					<Comment/>
					<ToolTip/>
					<FillChecking>DontCheck</FillChecking>
					<StandardAttributes>
						<xr:StandardAttribute name="LineNumber">
							<xr:LinkByType/>
							<xr:FillChecking>DontCheck</xr:FillChecking>
							<xr:MultiLine>false</xr:MultiLine>
							<xr:FillFromFillingValue>false</xr:FillFromFillingValue>
							<xr:CreateOnInput>Auto</xr:CreateOnInput>
							<xr:MaxValue xsi:nil="true"/>
							<xr:ToolTip/>
							<xr:ExtendedEdit>false</xr:ExtendedEdit>
							<xr:Format/>
							<xr:ChoiceForm/>
							<xr:QuickChoice>Auto</xr:QuickChoice>
							<xr:ChoiceHistoryOnInput>Auto</xr:ChoiceHistoryOnInput>
							<xr:EditFormat/>
							<xr:PasswordMode>false</xr:PasswordMode>
							<xr:MarkNegatives>false</xr:MarkNegatives>
							<xr:MinValue xsi:nil="true"/>
							<xr:Synonym/>
							<xr:Comment/>
							<xr:FullTextSearch>Use</xr:FullTextSearch>
							<xr:ChoiceParameterLinks/>
							<xr:FillValue xsi:nil="true"/>
							<xr:Mask/>
							<xr:ChoiceParameters/>
						</xr:StandardAttribute>
					</StandardAttributes>
				</Properties>
				<ChildObjects>
					<Attribute uuid="cf729dec-560f-42cd-982a-36414793499b">
						<Properties>
							<Name>КлючСвязи</Name>
							<Synonym>
								<v8:item>
									<v8:lang>ru</v8:lang>
									<v8:content>Ключ связи</v8:content>
								</v8:item>
							</Synonym>
							<Comment/>
							<Type>
								<v8:Type>xs:decimal</v8:Type>
								<v8:NumberQualifiers>
									<v8:Digits>5</v8:Digits>
									<v8:FractionDigits>0</v8:FractionDigits>
									<v8:AllowedSign>Nonnegative</v8:AllowedSign>
								</v8:NumberQualifiers>
							</Type>
							<PasswordMode>false</PasswordMode>
							<Format/>
							<EditFormat/>
							<ToolTip/>
							<MarkNegatives>false</MarkNegatives>
							<Mask/>
							<MultiLine>false</MultiLine>
							<ExtendedEdit>false</ExtendedEdit>
							<MinValue xsi:nil="true"/>
							<MaxValue xsi:nil="true"/>
							<FillChecking>DontCheck</FillChecking>
							<ChoiceFoldersAndItems>Items</ChoiceFoldersAndItems>
							<ChoiceParameterLinks/>
							<ChoiceParameters/>
							<QuickChoice>Auto</QuickChoice>
							<CreateOnInput>Auto</CreateOnInput>
							<ChoiceForm/>
							<LinkByType/>
							<ChoiceHistoryOnInput>Auto</ChoiceHistoryOnInput>
							<Indexing>Index</Indexing>
							<FullTextSearch>Use</FullTextSearch>
						</Properties>
					</Attribute>
					<Attribute uuid="14fb3ff0-a4a7-453e-b5e1-0259d14a0264">
						<Properties>
							<Name>guid</Name>
							<Synonym>
								<v8:item>
									<v8:lang>ru</v8:lang>
									<v8:content>Guid</v8:content>
								</v8:item>
							</Synonym>
							<Comment/>
							<Type>
								<v8:Type>xs:string</v8:Type>
								<v8:StringQualifiers>
									<v8:Length>50</v8:Length>
									<v8:AllowedLength>Variable</v8:AllowedLength>
								</v8:StringQualifiers>
							</Type>
							<PasswordMode>false</PasswordMode>
							<Format/>
							<EditFormat/>
							<ToolTip/>
							<MarkNegatives>false</MarkNegatives>
							<Mask/>
							<MultiLine>false</MultiLine>
							<ExtendedEdit>false</ExtendedEdit>
							<MinValue xsi:nil="true"/>
							<MaxValue xsi:nil="true"/>
							<FillChecking>DontCheck</FillChecking>
							<ChoiceFoldersAndItems>Items</ChoiceFoldersAndItems>
							<ChoiceParameterLinks/>
							<ChoiceParameters/>
							<QuickChoice>Auto</QuickChoice>
							<CreateOnInput>Auto</CreateOnInput>
							<ChoiceForm/>
							<LinkByType/>
							<ChoiceHistoryOnInput>Auto</ChoiceHistoryOnInput>
							<Indexing>DontIndex</Indexing>
							<FullTextSearch>Use</FullTextSearch>
						</Properties>
					</Attribute>
					<Attribute uuid="b7067f3d-f05b-4c1a-a41c-8e49420efb81">
						<Properties>
							<Name>Количество</Name>
							<Synonym>
								<v8:item>
									<v8:lang>ru</v8:lang>
									<v8:content>Количество</v8:content>
								</v8:item>
							</Synonym>
							<Comment/>
							<Type>
								<v8:Type>xs:decimal</v8:Type>
								<v8:NumberQualifiers>
									<v8:Digits>15</v8:Digits>
									<v8:FractionDigits>3</v8:FractionDigits>
									<v8:AllowedSign>Any</v8:AllowedSign>
								</v8:NumberQualifiers>
							</Type>
							<PasswordMode>false</PasswordMode>
							<Format/>
							<EditFormat/>
							<ToolTip/>
							<MarkNegatives>false</MarkNegatives>
							<Mask/>
							<MultiLine>false</MultiLine>
							<ExtendedEdit>false</ExtendedEdit>
							<MinValue xsi:nil="true"/>
							<MaxValue xsi:nil="true"/>
							<FillChecking>DontCheck</FillChecking>
							<ChoiceFoldersAndItems>Items</ChoiceFoldersAndItems>
							<ChoiceParameterLinks/>
							<ChoiceParameters/>
							<QuickChoice>Auto</QuickChoice>
							<CreateOnInput>Auto</CreateOnInput>
							<ChoiceForm/>
							<LinkByType/>
							<ChoiceHistoryOnInput>Auto</ChoiceHistoryOnInput>
							<Indexing>DontIndex</Indexing>
							<FullTextSearch>Use</FullTextSearch>
						</Properties>
					</Attribute>
					<Attribute uuid="bd5478fd-01ee-4021-9e28-43296b35b35f">
						<Properties>
							<Name>КоличествоМест</Name>
							<Synonym>
								<v8:item>
									<v8:lang>ru</v8:lang>
									<v8:content>Количество мест</v8:content>
								</v8:item>
							</Synonym>
							<Comment/>
							<Type>
								<v8:Type>xs:decimal</v8:Type>
								<v8:NumberQualifiers>
									<v8:Digits>15</v8:Digits>
									<v8:FractionDigits>3</v8:FractionDigits>
									<v8:AllowedSign>Any</v8:AllowedSign>
								</v8:NumberQualifiers>
							</Type>
							<PasswordMode>false</PasswordMode>
							<Format/>
							<EditFormat/>
							<ToolTip/>
							<MarkNegatives>false</MarkNegatives>
							<Mask/>
							<MultiLine>false</MultiLine>
							<ExtendedEdit>false</ExtendedEdit>
							<MinValue xsi:nil="true"/>
							<MaxValue xsi:nil="true"/>
							<FillChecking>DontCheck</FillChecking>
							<ChoiceFoldersAndItems>Items</ChoiceFoldersAndItems>
							<ChoiceParameterLinks/>
							<ChoiceParameters/>
							<QuickChoice>Auto</QuickChoice>
							<CreateOnInput>Auto</CreateOnInput>
							<ChoiceForm/>
							<LinkByType/>
							<ChoiceHistoryOnInput>Auto</ChoiceHistoryOnInput>
							<Indexing>DontIndex</Indexing>
							<FullTextSearch>Use</FullTextSearch>
						</Properties>
					</Attribute>
					<Attribute uuid="57a709eb-77dc-4c85-93be-a1fba4b71508">
						<Properties>
							<Name>Упаковка</Name>
							<Synonym>
								<v8:item>
									<v8:lang>ru</v8:lang>
									<v8:content>Упаковка</v8:content>
								</v8:item>
							</Synonym>
							<Comment/>
							<Type>
								<v8:TypeSet>cfg:DefinedType.ВетисPackingForm</v8:TypeSet>
							</Type>
							<PasswordMode>false</PasswordMode>
							<Format/>
							<EditFormat/>
							<ToolTip/>
							<MarkNegatives>false</MarkNegatives>
							<Mask/>
							<MultiLine>false</MultiLine>
							<ExtendedEdit>false</ExtendedEdit>
							<MinValue xsi:nil="true"/>
							<MaxValue xsi:nil="true"/>
							<FillChecking>DontCheck</FillChecking>
							<ChoiceFoldersAndItems>Items</ChoiceFoldersAndItems>
							<ChoiceParameterLinks/>
							<ChoiceParameters/>
							<QuickChoice>Auto</QuickChoice>
							<CreateOnInput>Auto</CreateOnInput>
							<ChoiceForm/>
							<LinkByType/>
							<ChoiceHistoryOnInput>Auto</ChoiceHistoryOnInput>
							<Indexing>DontIndex</Indexing>
							<FullTextSearch>Use</FullTextSearch>
						</Properties>
					</Attribute>
				</ChildObjects>
			</TabularSection>
			<TabularSection uuid="f06976b3-166a-40cd-af1b-3975081dd012">
				<InternalInfo>
					<xr:GeneratedType name="DocumentTabularSection.ВетисТранспортнаяПартия.ВСД" category="TabularSection">
						<xr:TypeId>84f2485c-8525-4740-aafb-80f861002dd9</xr:TypeId>
						<xr:ValueId>7f7df0c4-a70c-4ce4-ae72-13c45fc140b4</xr:ValueId>
					</xr:GeneratedType>
					<xr:GeneratedType name="DocumentTabularSectionRow.ВетисТранспортнаяПартия.ВСД" category="TabularSectionRow">
						<xr:TypeId>2e530259-c0ad-4ddf-9b8c-51d34fb78466</xr:TypeId>
						<xr:ValueId>039f61b8-5605-4fdc-89be-01482d98dc34</xr:ValueId>
					</xr:GeneratedType>
				</InternalInfo>
				<Properties>
					<Name>ВСД</Name>
					<Synonym>
						<v8:item>
							<v8:lang>ru</v8:lang>
							<v8:content>ВСД</v8:content>
						</v8:item>
					</Synonym>
					<Comment/>
					<ToolTip/>
					<FillChecking>DontCheck</FillChecking>
					<StandardAttributes>
						<xr:StandardAttribute name="LineNumber">
							<xr:LinkByType/>
							<xr:FillChecking>DontCheck</xr:FillChecking>
							<xr:MultiLine>false</xr:MultiLine>
							<xr:FillFromFillingValue>false</xr:FillFromFillingValue>
							<xr:CreateOnInput>Auto</xr:CreateOnInput>
							<xr:MaxValue xsi:nil="true"/>
							<xr:ToolTip/>
							<xr:ExtendedEdit>false</xr:ExtendedEdit>
							<xr:Format/>
							<xr:ChoiceForm/>
							<xr:QuickChoice>Auto</xr:QuickChoice>
							<xr:ChoiceHistoryOnInput>Auto</xr:ChoiceHistoryOnInput>
							<xr:EditFormat/>
							<xr:PasswordMode>false</xr:PasswordMode>
							<xr:MarkNegatives>false</xr:MarkNegatives>
							<xr:MinValue xsi:nil="true"/>
							<xr:Synonym/>
							<xr:Comment/>
							<xr:FullTextSearch>Use</xr:FullTextSearch>
							<xr:ChoiceParameterLinks/>
							<xr:FillValue xsi:nil="true"/>
							<xr:Mask/>
							<xr:ChoiceParameters/>
						</xr:StandardAttribute>
					</StandardAttributes>
				</Properties>
				<ChildObjects>
					<Attribute uuid="013cc127-c499-42c1-9e86-bf87a92ccb00">
						<Properties>
							<Name>НазначениеГруза</Name>
							<Synonym>
								<v8:item>
									<v8:lang>ru</v8:lang>
									<v8:content>Назначение груза</v8:content>
								</v8:item>
							</Synonym>
							<Comment/>
							<Type>
								<v8:TypeSet>cfg:DefinedType.ВетисPurpose</v8:TypeSet>
							</Type>
							<PasswordMode>false</PasswordMode>
							<Format/>
							<EditFormat/>
							<ToolTip/>
							<MarkNegatives>false</MarkNegatives>
							<Mask/>
							<MultiLine>false</MultiLine>
							<ExtendedEdit>false</ExtendedEdit>
							<MinValue xsi:nil="true"/>
							<MaxValue xsi:nil="true"/>
							<FillChecking>DontCheck</FillChecking>
							<ChoiceFoldersAndItems>Items</ChoiceFoldersAndItems>
							<ChoiceParameterLinks/>
							<ChoiceParameters/>
							<QuickChoice>Auto</QuickChoice>
							<CreateOnInput>Auto</CreateOnInput>
							<ChoiceForm/>
							<LinkByType/>
							<ChoiceHistoryOnInput>Auto</ChoiceHistoryOnInput>
							<Indexing>DontIndex</Indexing>
							<FullTextSearch>Use</FullTextSearch>
						</Properties>
					</Attribute>
					<Attribute uuid="e4e79d97-0c0f-4a1d-b90a-8c98e7e6dea5">
						<Properties>
							<Name>КонтрольГосВетврачем</Name>
							<Synonym>
								<v8:item>
									<v8:lang>ru</v8:lang>
									<v8:content>Контроль гос. ветврачем</v8:content>
								</v8:item>
							</Synonym>
							<Comment/>
							<Type>
								<v8:Type>xs:boolean</v8:Type>
							</Type>
							<PasswordMode>false</PasswordMode>
							<Format/>
							<EditFormat/>
							<ToolTip/>
							<MarkNegatives>false</MarkNegatives>
							<Mask/>
							<MultiLine>false</MultiLine>
							<ExtendedEdit>false</ExtendedEdit>
							<MinValue xsi:nil="true"/>
							<MaxValue xsi:nil="true"/>
							<FillChecking>DontCheck</FillChecking>
							<ChoiceFoldersAndItems>Items</ChoiceFoldersAndItems>
							<ChoiceParameterLinks/>
							<ChoiceParameters/>
							<QuickChoice>Auto</QuickChoice>
							<CreateOnInput>Auto</CreateOnInput>
							<ChoiceForm/>
							<LinkByType/>
							<ChoiceHistoryOnInput>Auto</ChoiceHistoryOnInput>
							<Indexing>DontIndex</Indexing>
							<FullTextSearch>Use</FullTextSearch>
						</Properties>
					</Attribute>
					<Attribute uuid="352032b0-b6fe-4b93-a11a-78645f542f42">
						<Properties>
							<Name>Ветсанэкспертиза</Name>
							<Synonym>
								<v8:item>
									<v8:lang>ru</v8:lang>
									<v8:content>Ветсанэкспертиза</v8:content>
								</v8:item>
							</Synonym>
							<Comment/>
							<Type>
								<v8:Type>xs:boolean</v8:Type>
							</Type>
							<PasswordMode>false</PasswordMode>
							<Format/>
							<EditFormat/>
							<ToolTip/>
							<MarkNegatives>false</MarkNegatives>
							<Mask/>
							<MultiLine>false</MultiLine>
							<ExtendedEdit>false</ExtendedEdit>
							<MinValue xsi:nil="true"/>
							<MaxValue xsi:nil="true"/>
							<FillChecking>DontCheck</FillChecking>
							<ChoiceFoldersAndItems>Items</ChoiceFoldersAndItems>
							<ChoiceParameterLinks/>
							<ChoiceParameters/>
							<QuickChoice>Auto</QuickChoice>
							<CreateOnInput>Auto</CreateOnInput>
							<ChoiceForm/>
							<LinkByType/>
							<ChoiceHistoryOnInput>Auto</ChoiceHistoryOnInput>
							<Indexing>DontIndex</Indexing>
							<FullTextSearch>Use</FullTextSearch>
						</Properties>
					</Attribute>
					<Attribute uuid="00dcf8e1-3de6-4982-ba7c-e0e2f58882b1">
						<Properties>
							<Name>ЛабораторныеИсследования</Name>
							<Synonym>
								<v8:item>
									<v8:lang>ru</v8:lang>
									<v8:content>Лабораторные исследования</v8:content>
								</v8:item>
							</Synonym>
							<Comment/>
							<Type>
								<v8:Type>xs:string</v8:Type>
								<v8:StringQualifiers>
									<v8:Length>0</v8:Length>
									<v8:AllowedLength>Variable</v8:AllowedLength>
								</v8:StringQualifiers>
							</Type>
							<PasswordMode>false</PasswordMode>
							<Format/>
							<EditFormat/>
							<ToolTip/>
							<MarkNegatives>false</MarkNegatives>
							<Mask/>
							<MultiLine>false</MultiLine>
							<ExtendedEdit>false</ExtendedEdit>
							<MinValue xsi:nil="true"/>
							<MaxValue xsi:nil="true"/>
							<FillChecking>DontCheck</FillChecking>
							<ChoiceFoldersAndItems>Items</ChoiceFoldersAndItems>
							<ChoiceParameterLinks/>
							<ChoiceParameters/>
							<QuickChoice>Auto</QuickChoice>
							<CreateOnInput>Auto</CreateOnInput>
							<ChoiceForm/>
							<LinkByType/>
							<ChoiceHistoryOnInput>Auto</ChoiceHistoryOnInput>
							<Indexing>DontIndex</Indexing>
							<FullTextSearch>Use</FullTextSearch>
						</Properties>
					</Attribute>
					<Attribute uuid="1d334959-6e06-4cba-af9a-1e9952265a88">
						<Properties>
							<Name>БлагополучиеМестности</Name>
							<Synonym>
								<v8:item>
									<v8:lang>ru</v8:lang>
									<v8:content>Благополучие местности</v8:content>
								</v8:item>
							</Synonym>
							<Comment/>
							<Type>
								<v8:Type>xs:string</v8:Type>
								<v8:StringQualifiers>
									<v8:Length>50</v8:Length>
									<v8:AllowedLength>Variable</v8:AllowedLength>
								</v8:StringQualifiers>
							</Type>
							<PasswordMode>false</PasswordMode>
							<Format/>
							<EditFormat/>
							<ToolTip/>
							<MarkNegatives>false</MarkNegatives>
							<Mask/>
							<MultiLine>false</MultiLine>
							<ExtendedEdit>false</ExtendedEdit>
							<MinValue xsi:nil="true"/>
							<MaxValue xsi:nil="true"/>
							<FillChecking>DontCheck</FillChecking>
							<ChoiceFoldersAndItems>Items</ChoiceFoldersAndItems>
							<ChoiceParameterLinks/>
							<ChoiceParameters/>
							<QuickChoice>Auto</QuickChoice>
							<CreateOnInput>Auto</CreateOnInput>
							<ChoiceForm/>
							<LinkByType/>
							<ChoiceHistoryOnInput>Auto</ChoiceHistoryOnInput>
							<Indexing>DontIndex</Indexing>
							<FullTextSearch>Use</FullTextSearch>
						</Properties>
					</Attribute>
				</ChildObjects>
			</TabularSection>
			<TabularSection uuid="4bcd8c59-d1ce-4697-b745-51ea9f4ede71">
				<InternalInfo>
					<xr:GeneratedType name="DocumentTabularSection.ВетисТранспортнаяПартия.ТТН" category="TabularSection">
						<xr:TypeId>645b3863-7e46-4c54-9885-f00fdc7cd5e5</xr:TypeId>
						<xr:ValueId>d68e4efe-e360-41e7-b140-ced09f2bbf8d</xr:ValueId>
					</xr:GeneratedType>
					<xr:GeneratedType name="DocumentTabularSectionRow.ВетисТранспортнаяПартия.ТТН" category="TabularSectionRow">
						<xr:TypeId>271c6517-d0f4-455f-b7ae-aa0ffb4df02f</xr:TypeId>
						<xr:ValueId>2b1b100d-b85a-4b2e-ae23-73d1edd48fe3</xr:ValueId>
					</xr:GeneratedType>
				</InternalInfo>
				<Properties>
					<Name>ТТН</Name>
					<Synonym>
						<v8:item>
							<v8:lang>ru</v8:lang>
							<v8:content>ТТН</v8:content>
						</v8:item>
					</Synonym>
					<Comment/>
					<ToolTip/>
					<FillChecking>DontCheck</FillChecking>
					<StandardAttributes>
						<xr:StandardAttribute name="LineNumber">
							<xr:LinkByType/>
							<xr:FillChecking>DontCheck</xr:FillChecking>
							<xr:MultiLine>false</xr:MultiLine>
							<xr:FillFromFillingValue>false</xr:FillFromFillingValue>
							<xr:CreateOnInput>Auto</xr:CreateOnInput>
							<xr:MaxValue xsi:nil="true"/>
							<xr:ToolTip/>
							<xr:ExtendedEdit>false</xr:ExtendedEdit>
							<xr:Format/>
							<xr:ChoiceForm/>
							<xr:QuickChoice>Auto</xr:QuickChoice>
							<xr:ChoiceHistoryOnInput>Auto</xr:ChoiceHistoryOnInput>
							<xr:EditFormat/>
							<xr:PasswordMode>false</xr:PasswordMode>
							<xr:MarkNegatives>false</xr:MarkNegatives>
							<xr:MinValue xsi:nil="true"/>
							<xr:Synonym/>
							<xr:Comment/>
							<xr:FullTextSearch>Use</xr:FullTextSearch>
							<xr:ChoiceParameterLinks/>
							<xr:FillValue xsi:nil="true"/>
							<xr:Mask/>
							<xr:ChoiceParameters/>
						</xr:StandardAttribute>
					</StandardAttributes>
				</Properties>
				<ChildObjects>
					<Attribute uuid="c0d669b0-b22f-4b4a-bae9-481df17bac3b">
						<Properties>
							<Name>Серия</Name>
							<Synonym>
								<v8:item>
									<v8:lang>ru</v8:lang>
									<v8:content>Серия</v8:content>
								</v8:item>
							</Synonym>
							<Comment/>
							<Type>
								<v8:Type>xs:string</v8:Type>
								<v8:StringQualifiers>
									<v8:Length>10</v8:Length>
									<v8:AllowedLength>Variable</v8:AllowedLength>
								</v8:StringQualifiers>
							</Type>
							<PasswordMode>false</PasswordMode>
							<Format/>
							<EditFormat/>
							<ToolTip/>
							<MarkNegatives>false</MarkNegatives>
							<Mask/>
							<MultiLine>false</MultiLine>
							<ExtendedEdit>false</ExtendedEdit>
							<MinValue xsi:nil="true"/>
							<MaxValue xsi:nil="true"/>
							<FillChecking>DontCheck</FillChecking>
							<ChoiceFoldersAndItems>Items</ChoiceFoldersAndItems>
							<ChoiceParameterLinks/>
							<ChoiceParameters/>
							<QuickChoice>Auto</QuickChoice>
							<CreateOnInput>Auto</CreateOnInput>
							<ChoiceForm/>
							<LinkByType/>
							<ChoiceHistoryOnInput>Auto</ChoiceHistoryOnInput>
							<Indexing>DontIndex</Indexing>
							<FullTextSearch>Use</FullTextSearch>
						</Properties>
					</Attribute>
					<Attribute uuid="068fd56c-9f67-4a60-9aa1-58bd31ea1b86">
						<Properties>
							<Name>Номер</Name>
							<Synonym>
								<v8:item>
									<v8:lang>ru</v8:lang>
									<v8:content>Номер</v8:content>
								</v8:item>
							</Synonym>
							<Comment/>
							<Type>
								<v8:Type>xs:string</v8:Type>
								<v8:StringQualifiers>
									<v8:Length>10</v8:Length>
									<v8:AllowedLength>Variable</v8:AllowedLength>
								</v8:StringQualifiers>
							</Type>
							<PasswordMode>false</PasswordMode>
							<Format/>
							<EditFormat/>
							<ToolTip/>
							<MarkNegatives>false</MarkNegatives>
							<Mask/>
							<MultiLine>false</MultiLine>
							<ExtendedEdit>false</ExtendedEdit>
							<MinValue xsi:nil="true"/>
							<MaxValue xsi:nil="true"/>
							<FillChecking>DontCheck</FillChecking>
							<ChoiceFoldersAndItems>Items</ChoiceFoldersAndItems>
							<ChoiceParameterLinks/>
							<ChoiceParameters/>
							<QuickChoice>Auto</QuickChoice>
							<CreateOnInput>Auto</CreateOnInput>
							<ChoiceForm/>
							<LinkByType/>
							<ChoiceHistoryOnInput>Auto</ChoiceHistoryOnInput>
							<Indexing>DontIndex</Indexing>
							<FullTextSearch>Use</FullTextSearch>
						</Properties>
					</Attribute>
					<Attribute uuid="e75b2d31-a785-4908-ab8c-4968f2933fae">
						<Properties>
							<Name>Дата</Name>
							<Synonym>
								<v8:item>
									<v8:lang>ru</v8:lang>
									<v8:content>Дата</v8:content>
								</v8:item>
							</Synonym>
							<Comment/>
							<Type>
								<v8:Type>xs:dateTime</v8:Type>
								<v8:DateQualifiers>
									<v8:DateFractions>DateTime</v8:DateFractions>
								</v8:DateQualifiers>
							</Type>
							<PasswordMode>false</PasswordMode>
							<Format/>
							<EditFormat/>
							<ToolTip/>
							<MarkNegatives>false</MarkNegatives>
							<Mask/>
							<MultiLine>false</MultiLine>
							<ExtendedEdit>false</ExtendedEdit>
							<MinValue xsi:nil="true"/>
							<MaxValue xsi:nil="true"/>
							<FillChecking>DontCheck</FillChecking>
							<ChoiceFoldersAndItems>Items</ChoiceFoldersAndItems>
							<ChoiceParameterLinks/>
							<ChoiceParameters/>
							<QuickChoice>Auto</QuickChoice>
							<CreateOnInput>Auto</CreateOnInput>
							<ChoiceForm/>
							<LinkByType/>
							<ChoiceHistoryOnInput>Auto</ChoiceHistoryOnInput>
							<Indexing>DontIndex</Indexing>
							<FullTextSearch>Use</FullTextSearch>
						</Properties>
					</Attribute>
					<Attribute uuid="2faba859-d537-44f6-8f2b-3082fbcb55ca">
						<Properties>
							<Name>Тип</Name>
							<Synonym>
								<v8:item>
									<v8:lang>ru</v8:lang>
									<v8:content>Тип</v8:content>
								</v8:item>
							</Synonym>
							<Comment/>
							<Type>
								<v8:Type>cfg:EnumRef.ВетисDocumentType</v8:Type>
							</Type>
							<PasswordMode>false</PasswordMode>
							<Format/>
							<EditFormat/>
							<ToolTip/>
							<MarkNegatives>false</MarkNegatives>
							<Mask/>
							<MultiLine>false</MultiLine>
							<ExtendedEdit>false</ExtendedEdit>
							<MinValue xsi:nil="true"/>
							<MaxValue xsi:nil="true"/>
							<FillChecking>DontCheck</FillChecking>
							<ChoiceFoldersAndItems>Items</ChoiceFoldersAndItems>
							<ChoiceParameterLinks/>
							<ChoiceParameters/>
							<QuickChoice>Auto</QuickChoice>
							<CreateOnInput>Auto</CreateOnInput>
							<ChoiceForm/>
							<LinkByType/>
							<ChoiceHistoryOnInput>Auto</ChoiceHistoryOnInput>
							<Indexing>DontIndex</Indexing>
							<FullTextSearch>Use</FullTextSearch>
						</Properties>
					</Attribute>
					<Attribute uuid="92f8d8eb-c82d-41df-bd35-3e2052c0d225">
						<Properties>
							<Name>Транспорт</Name>
							<Synonym>
								<v8:item>
									<v8:lang>ru</v8:lang>
									<v8:content>Транспорт</v8:content>
								</v8:item>
							</Synonym>
							<Comment/>
							<Type>
								<v8:TypeSet>cfg:DefinedType.ВетисTransport</v8:TypeSet>
							</Type>
							<PasswordMode>false</PasswordMode>
							<Format/>
							<EditFormat/>
							<ToolTip/>
							<MarkNegatives>false</MarkNegatives>
							<Mask/>
							<MultiLine>false</MultiLine>
							<ExtendedEdit>false</ExtendedEdit>
							<MinValue xsi:nil="true"/>
							<MaxValue xsi:nil="true"/>
							<FillChecking>ShowError</FillChecking>
							<ChoiceFoldersAndItems>Items</ChoiceFoldersAndItems>
							<ChoiceParameterLinks/>
							<ChoiceParameters/>
							<QuickChoice>Auto</QuickChoice>
							<CreateOnInput>Auto</CreateOnInput>
							<ChoiceForm/>
							<LinkByType/>
							<ChoiceHistoryOnInput>Auto</ChoiceHistoryOnInput>
							<Indexing>DontIndex</Indexing>
							<FullTextSearch>Use</FullTextSearch>
						</Properties>
					</Attribute>
					<Attribute uuid="d6101858-e5b9-4661-99de-1b0746874295">
						<Properties>
							<Name>СпособХранения</Name>
							<Synonym>
								<v8:item>
									<v8:lang>ru</v8:lang>
									<v8:content>Способ хранения</v8:content>
								</v8:item>
							</Synonym>
							<Comment/>
							<Type>
								<v8:Type>cfg:EnumRef.ВетисTransportStorageType</v8:Type>
							</Type>
							<PasswordMode>false</PasswordMode>
							<Format/>
							<EditFormat/>
							<ToolTip/>
							<MarkNegatives>false</MarkNegatives>
							<Mask/>
							<MultiLine>false</MultiLine>
							<ExtendedEdit>false</ExtendedEdit>
							<MinValue xsi:nil="true"/>
							<MaxValue xsi:nil="true"/>
							<FillChecking>DontCheck</FillChecking>
							<ChoiceFoldersAndItems>Items</ChoiceFoldersAndItems>
							<ChoiceParameterLinks/>
							<ChoiceParameters/>
							<QuickChoice>Auto</QuickChoice>
							<CreateOnInput>Auto</CreateOnInput>
							<ChoiceForm/>
							<LinkByType/>
							<ChoiceHistoryOnInput>Auto</ChoiceHistoryOnInput>
							<Indexing>DontIndex</Indexing>
							<FullTextSearch>Use</FullTextSearch>
						</Properties>
					</Attribute>
				</ChildObjects>
			</TabularSection>
		</ChildObjects>
	</Document>
</MetaDataObject>