<?xml version="1.0" encoding="UTF-8"?>
<MetaDataObject xmlns="http://v8.1c.ru/8.3/MDClasses" xmlns:app="http://v8.1c.ru/8.2/managed-application/core" xmlns:cfg="http://v8.1c.ru/8.1/data/enterprise/current-config" xmlns:cmi="http://v8.1c.ru/8.2/managed-application/cmi" xmlns:ent="http://v8.1c.ru/8.1/data/enterprise" xmlns:lf="http://v8.1c.ru/8.2/managed-application/logform" xmlns:style="http://v8.1c.ru/8.1/data/ui/style" xmlns:sys="http://v8.1c.ru/8.1/data/ui/fonts/system" xmlns:v8="http://v8.1c.ru/8.1/data/core" xmlns:v8ui="http://v8.1c.ru/8.1/data/ui" xmlns:web="http://v8.1c.ru/8.1/data/ui/colors/web" xmlns:win="http://v8.1c.ru/8.1/data/ui/colors/windows" xmlns:xen="http://v8.1c.ru/8.3/xcf/enums" xmlns:xpr="http://v8.1c.ru/8.3/xcf/predef" xmlns:xr="http://v8.1c.ru/8.3/xcf/readable" xmlns:xs="http://www.w3.org/2001/XMLSchema" xmlns:xsi="http://www.w3.org/2001/XMLSchema-instance" version="2.4">
	<InformationRegister uuid="93ffa0e9-0d26-49ed-bd27-59a589e833a6">
		<InternalInfo>
			<xr:GeneratedType name="InformationRegisterRecord.ВетисМногоуровневаяУпаковка" category="Record">
				<xr:TypeId>1c57b129-d6a7-469d-a3cb-48c88df7ca68</xr:TypeId>
				<xr:ValueId>95c69525-22fb-47ea-8608-c33b28ea8669</xr:ValueId>
			</xr:GeneratedType>
			<xr:GeneratedType name="InformationRegisterManager.ВетисМногоуровневаяУпаковка" category="Manager">
				<xr:TypeId>311e6973-f4a9-4cb8-9e66-effd3c24ee44</xr:TypeId>
				<xr:ValueId>d4a9cab8-659f-44e6-9d6b-f9d46d279cda</xr:ValueId>
			</xr:GeneratedType>
			<xr:GeneratedType name="InformationRegisterSelection.ВетисМногоуровневаяУпаковка" category="Selection">
				<xr:TypeId>9425b08f-4fd2-47c5-a88f-736cb4786cd0</xr:TypeId>
				<xr:ValueId>e1c9efb5-acb7-431f-9231-48233983ea9d</xr:ValueId>
			</xr:GeneratedType>
			<xr:GeneratedType name="InformationRegisterList.ВетисМногоуровневаяУпаковка" category="List">
				<xr:TypeId>4e71645c-aed7-471a-a263-2f5a985df44b</xr:TypeId>
				<xr:ValueId>15305c82-330a-46c9-b9dd-431782d20c8a</xr:ValueId>
			</xr:GeneratedType>
			<xr:GeneratedType name="InformationRegisterRecordSet.ВетисМногоуровневаяУпаковка" category="RecordSet">
				<xr:TypeId>c4a06380-e4a5-4b6a-88d9-0a8dea41b57c</xr:TypeId>
				<xr:ValueId>2a380c7b-28ce-4f12-be2f-5a88aefc3d34</xr:ValueId>
			</xr:GeneratedType>
			<xr:GeneratedType name="InformationRegisterRecordKey.ВетисМногоуровневаяУпаковка" category="RecordKey">
				<xr:TypeId>36882ecc-c102-4965-bcaa-aefbf1d5ac24</xr:TypeId>
				<xr:ValueId>c8520c3b-8c0a-4858-b432-4e04f563a9b4</xr:ValueId>
			</xr:GeneratedType>
			<xr:GeneratedType name="InformationRegisterRecordManager.ВетисМногоуровневаяУпаковка" category="RecordManager">
				<xr:TypeId>1e54575b-d97c-431a-8d14-5508cf433095</xr:TypeId>
				<xr:ValueId>bc916505-9160-4970-8681-7a011bb20851</xr:ValueId>
			</xr:GeneratedType>
		</InternalInfo>
		<Properties>
			<Name>ВетисМногоуровневаяУпаковка</Name>
			<Synonym>
				<v8:item>
					<v8:lang>ru</v8:lang>
					<v8:content>Многоуровневая упаковка (ветис)</v8:content>
				</v8:item>
			</Synonym>
			<Comment/>
			<UseStandardCommands>false</UseStandardCommands>
			<EditType>InDialog</EditType>
			<DefaultRecordForm/>
			<DefaultListForm/>
			<AuxiliaryRecordForm/>
			<AuxiliaryListForm/>
			<InformationRegisterPeriodicity>Nonperiodical</InformationRegisterPeriodicity>
			<WriteMode>Independent</WriteMode>
			<MainFilterOnPeriod>false</MainFilterOnPeriod>
			<IncludeHelpInContents>false</IncludeHelpInContents>
			<DataLockControlMode>Managed</DataLockControlMode>
			<FullTextSearch>DontUse</FullTextSearch>
			<EnableTotalsSliceFirst>false</EnableTotalsSliceFirst>
			<EnableTotalsSliceLast>false</EnableTotalsSliceLast>
			<RecordPresentation/>
			<ExtendedRecordPresentation/>
			<ListPresentation/>
			<ExtendedListPresentation/>
			<Explanation/>
		</Properties>
		<ChildObjects>
			<Dimension uuid="1c4d1699-1cb3-49b4-8ac8-6a47d82c4cfa">
				<Properties>
					<Name>Номенклатура</Name>
					<Synonym>
						<v8:item>
							<v8:lang>ru</v8:lang>
							<v8:content>Номенклатура</v8:content>
						</v8:item>
					</Synonym>
					<Comment/>
					<Type>
						<v8:Type>cfg:CatalogRef.Номенклатура</v8:Type>
					</Type>
					<PasswordMode>false</PasswordMode>
					<Format/>
					<EditFormat/>
					<ToolTip/>
					<MarkNegatives>false</MarkNegatives>
					<Mask/>
					<MultiLine>false</MultiLine>
					<ExtendedEdit>false</ExtendedEdit>
					<MinValue xsi:nil="true"/>
					<MaxValue xsi:nil="true"/>
					<FillFromFillingValue>false</FillFromFillingValue>
					<FillValue xsi:nil="true"/>
					<FillChecking>DontCheck</FillChecking>
					<ChoiceFoldersAndItems>Items</ChoiceFoldersAndItems>
					<ChoiceParameterLinks/>
					<ChoiceParameters/>
					<QuickChoice>Auto</QuickChoice>
					<CreateOnInput>Auto</CreateOnInput>
					<ChoiceForm/>
					<LinkByType/>
					<ChoiceHistoryOnInput>Auto</ChoiceHistoryOnInput>
					<Master>false</Master>
					<MainFilter>true</MainFilter>
					<DenyIncompleteValues>false</DenyIncompleteValues>
					<Indexing>DontIndex</Indexing>
					<FullTextSearch>Use</FullTextSearch>
				</Properties>
			</Dimension>
			<Dimension uuid="e37c7453-bca7-4f49-8521-54857cbbdbe3">
				<Properties>
					<Name>Уровень</Name>
					<Synonym>
						<v8:item>
							<v8:lang>ru</v8:lang>
							<v8:content>Уровень</v8:content>
						</v8:item>
					</Synonym>
					<Comment>level {dt:PackageLevelType}</Comment>
					<Type>
						<v8:Type>cfg:EnumRef.ВетисPackageLevelType</v8:Type>
					</Type>
					<PasswordMode>false</PasswordMode>
					<Format/>
					<EditFormat/>
					<ToolTip/>
					<MarkNegatives>false</MarkNegatives>
					<Mask/>
					<MultiLine>false</MultiLine>
					<ExtendedEdit>false</ExtendedEdit>
					<MinValue xsi:nil="true"/>
					<MaxValue xsi:nil="true"/>
					<FillFromFillingValue>false</FillFromFillingValue>
					<FillValue xsi:nil="true"/>
					<FillChecking>ShowError</FillChecking>
					<ChoiceFoldersAndItems>Items</ChoiceFoldersAndItems>
					<ChoiceParameterLinks/>
					<ChoiceParameters/>
					<QuickChoice>Auto</QuickChoice>
					<CreateOnInput>Auto</CreateOnInput>
					<ChoiceForm/>
					<LinkByType/>
					<ChoiceHistoryOnInput>Auto</ChoiceHistoryOnInput>
					<Master>false</Master>
					<MainFilter>true</MainFilter>
					<DenyIncompleteValues>false</DenyIncompleteValues>
					<Indexing>DontIndex</Indexing>
					<FullTextSearch>Use</FullTextSearch>
				</Properties>
			</Dimension>
			<Dimension uuid="9089c60c-6ae2-437a-9c9d-fcf8b8079453">
				<Properties>
					<Name>Упаковка</Name>
					<Synonym>
						<v8:item>
							<v8:lang>ru</v8:lang>
							<v8:content>Упаковка</v8:content>
						</v8:item>
					</Synonym>
					<Comment>packingType {dt:PackingType}</Comment>
					<Type>
						<v8:Type>cfg:CatalogRef.ВетисPackingForm</v8:Type>
					</Type>
					<PasswordMode>false</PasswordMode>
					<Format/>
					<EditFormat/>
					<ToolTip/>
					<MarkNegatives>false</MarkNegatives>
					<Mask/>
					<MultiLine>false</MultiLine>
					<ExtendedEdit>false</ExtendedEdit>
					<MinValue xsi:nil="true"/>
					<MaxValue xsi:nil="true"/>
					<FillFromFillingValue>false</FillFromFillingValue>
					<FillValue xsi:nil="true"/>
					<FillChecking>ShowError</FillChecking>
					<ChoiceFoldersAndItems>Items</ChoiceFoldersAndItems>
					<ChoiceParameterLinks/>
					<ChoiceParameters/>
					<QuickChoice>Auto</QuickChoice>
					<CreateOnInput>Auto</CreateOnInput>
					<ChoiceForm/>
					<LinkByType/>
					<ChoiceHistoryOnInput>Auto</ChoiceHistoryOnInput>
					<Master>false</Master>
					<MainFilter>true</MainFilter>
					<DenyIncompleteValues>false</DenyIncompleteValues>
					<Indexing>DontIndex</Indexing>
					<FullTextSearch>Use</FullTextSearch>
				</Properties>
			</Dimension>
			<Dimension uuid="5c9220b5-8a45-48e5-bb93-bbfb5872e4d4">
				<Properties>
					<Name>Количество</Name>
					<Synonym>
						<v8:item>
							<v8:lang>ru</v8:lang>
							<v8:content>Количество</v8:content>
						</v8:item>
					</Synonym>
					<Comment>quantity {xs:integer}</Comment>
					<Type>
						<v8:Type>xs:decimal</v8:Type>
						<v8:NumberQualifiers>
							<v8:Digits>15</v8:Digits>
							<v8:FractionDigits>0</v8:FractionDigits>
							<v8:AllowedSign>Any</v8:AllowedSign>
						</v8:NumberQualifiers>
					</Type>
					<PasswordMode>false</PasswordMode>
					<Format/>
					<EditFormat/>
					<ToolTip/>
					<MarkNegatives>false</MarkNegatives>
					<Mask/>
					<MultiLine>false</MultiLine>
					<ExtendedEdit>false</ExtendedEdit>
					<MinValue xsi:nil="true"/>
					<MaxValue xsi:nil="true"/>
					<FillFromFillingValue>false</FillFromFillingValue>
					<FillValue xsi:nil="true"/>
					<FillChecking>DontCheck</FillChecking>
					<ChoiceFoldersAndItems>Items</ChoiceFoldersAndItems>
					<ChoiceParameterLinks/>
					<ChoiceParameters/>
					<QuickChoice>Auto</QuickChoice>
					<CreateOnInput>Auto</CreateOnInput>
					<ChoiceForm/>
					<LinkByType/>
					<ChoiceHistoryOnInput>Auto</ChoiceHistoryOnInput>
					<Master>false</Master>
					<MainFilter>true</MainFilter>
					<DenyIncompleteValues>false</DenyIncompleteValues>
					<Indexing>DontIndex</Indexing>
					<FullTextSearch>Use</FullTextSearch>
				</Properties>
			</Dimension>
		</ChildObjects>
	</InformationRegister>
</MetaDataObject>